[{"code":968,"name":"BHASKAR BHAT","email":"BHASKARB@TITAN.CO.IN","level":"0","dept":"MD OFFICE","number":9845650141},
{"code":1170,"name":"MALINI H G","email":"MALINI@TITAN.CO.IN","level":"L7","dept":"COO'S OFFICE-WATCH DIVISION","number":9880244566},
{"code":1697,"name":"RONNIE TALATI","email":"RATALATI@TITAN.CO.IN","level":"1","dept":"MARKETING-FASTRACK","number":0},
{"code":4131,"name":"LORNA LOBO","email":"LOLO@TITAN.CO.IN","level":"L9","dept":"BUSINESS ETHICS","number":9980143035},
{"code":5387,"name":"PALANI KUMAR A","email":"PALANIKUMARA@TITAN.CO.IN","level":"3","dept":"INTEGRATED RETAIL SERVICES","number":9244545001},
{"code":7189,"name":"BASKAR A","email":"BHASKARA@TITAN.CO.IN","level":"L5","dept":"DESIGNS-TANISHQ","number":9243462489},
{"code":11244,"name":"NAGARAJ B V","email":"NAGARAJBV@TITAN.CO.IN","level":"GM","dept":"CENTRAL TECHNOLOGY SERVICES","number":9845742205},
{"code":14119,"name":"GOVIND RAJ V","email":"GOVINDRAJV@TITAN.CO.IN","level":"1","dept":"SALES-CERAMIC PRODUCTS","number":9243446795},
{"code":20331,"name":"MALLANA GOUDAR E L","email":"MALLANAGOUDAR@TITAN.CO.IN","level":"L5","dept":"CENTRAL TECHNOLOGY SERVICES","number":9448093242},
{"code":21404,"name":"ARUN KUMAR P","email":"ARUNKUMAR@TITAN.CO.IN","level":"L8","dept":"HUMAN RESOURCES","number":9901973600},
{"code":23120,"name":"SUNDER R","email":"SUNDERR@TITAN.CO.IN","level":"L8","dept":"FINANCE","number":8026762048},
{"code":23905,"name":"SUKUMARAN K S","email":"SUKUMAR@TITAN.CO.IN","level":"L5","dept":"FINANCE","number":9379188686},
{"code":24021,"name":"GANESH S H","email":"GANESHSH@TITAN.CO.IN","level":"L9","dept":"FINANCE","number":9611999466},
{"code":25535,"name":"SRINIVASA NAIRY","email":"NAIRY@TITAN.CO.IN","level":"4","dept":"FINANCE","number":9845550359},
{"code":27509,"name":"RAVI M","email":"RAVIM@TITAN.CO.IN","level":"L5","dept":"PURCHASE","number":9449959012},
{"code":27864,"name":"KARKERA R","email":"KARKERARG@TITAN.CO.IN","level":"5","dept":"FINANCE","number":9845392933},
{"code":29752,"name":"MUNISWAMY RAJA G","email":"RAJAGM@TITAN.CO.IN","level":"L5","dept":"SUPPLY CHAIN MANAGEMENT","number":0},
{"code":32734,"name":"LINGESH BABU K","email":"LINGESHB@TITAN.CO.IN","level":"L9","dept":"CUSTOMER SERVICE DEPARTMENT","number":0},
{"code":39041,"name":"MOPURI DWARAKANATH","email":"DWARAK@TITAN.CO.IN","level":"L9","dept":"INTERNATIONAL OPERATIONS - TPD","number":9880693939},
{"code":39396,"name":"NIRANJAN H","email":"NIRANJANH@TITAN.CO.IN","level":"L9","dept":"FINANCE","number":9845589696},
{"code":46939,"name":"MOORTHY C","email":"MOORTHYC@TITAN.CO.IN","level":"L4","dept":"RETAILING-GOLD PLUS","number":9842864024},
{"code":49728,"name":"SRINIVASAN C","email":"SRINIC@TITAN.CO.IN","level":"1","dept":"TRADE WATCHES","number":9740016575},
{"code":51465,"name":"PRABHAKARAN R","email":"PRABAKARANR@TITAN.CO.IN","level":"L5","dept":"RETAIL PROJECTS","number":9972177654},
{"code":53880,"name":"JAYAPRAKASH B S","email":"JAYAPRAKASH@TITAN.CO.IN","level":"L6","dept":"DESIGNS","number":9632222665},
{"code":58030,"name":"CHIDANAND A C","email":"CHIDANAND@TITAN.CO.IN","level":"4","dept":"SYSTEMS","number":0},
{"code":58202,"name":"SASIKALA G C","email":"SASHIKALA@TITAN.CO.IN","level":"L9","dept":"SYSTEMS","number":9980196322},
{"code":63255,"name":"NATARAJAN S","email":"SNRAJAN@TITAN.CO.IN","level":"L5","dept":"MERCHANDISING-GOLD PLUS","number":9443325059},
{"code":64769,"name":"RAMESH B N","email":"RAMESHB@TITAN.CO.IN","level":"L6","dept":"SYSTEMS","number":9880302479},
{"code":67644,"name":"BALAPPA N","email":"BALAPPA@TITAN.CO.IN","level":"L8","dept":"FINANCE","number":9945847166},
{"code":70454,"name":"RAVI KANT S","email":"RAVI@TITAN.CO.IN","level":"CEO","dept":"GENERAL-EYEWEAR","number":0},
{"code":74316,"name":"AMAR S P","email":"AMARSP@TITAN.CO.IN","level":"L9","dept":"FINANCE-EYEWEAR","number":9845713234},
{"code":74402,"name":"SANDEEP KULHALLI","email":"SANDEEPK@TITAN.CO.IN","level":"1","dept":"SALES-TANISHQ","number":0},
{"code":79789,"name":"SRINIVASAN A R","email":"SRINIVASANAR@TITAN.CO.IN","level":"L9","dept":"TRADE WATCHES","number":9740984300},
{"code":81956,"name":"SUDEVAN P V","email":"SUDEVAN@TITAN.CO.IN","level":"L8","dept":"CENTRAL TECHNOLOGY SERVICES","number":9980521322},
{"code":83145,"name":"KUMAR S","email":"KUMAR@TITAN.CO.IN","level":"L7","dept":"SYSTEMS","number":9980529422},
{"code":85033,"name":"SHIVA PRAKASH B G","email":"SHIVAPBG@TITAN.CO.IN","level":"L6","dept":"CORPORATE SALES","number":9845650152},
{"code":85388,"name":"JAYSHANKAR MENON","email":"JAYSHANKARM@TITAN.CO.IN","level":"L9","dept":"FRAGRANCES-SALES","number":9845735507},
{"code":87620,"name":"RAGHAVENDRA R","email":"RAGHAVENDRAR@TITAN.CO.IN","level":"L5","dept":"DESIGNS","number":9901771237},
{"code":88962,"name":"SUBASH S","email":"SUBHASH@TITAN.CO.IN","level":"5","dept":"RETAIL PROJECTS","number":9880502559},
{"code":90258,"name":"RAMASWAMY S V","email":"RAMASWAMY@TITAN.CO.IN","level":"L8","dept":"FINANCE","number":9980014715},
{"code":90602,"name":"BASKARAN M","email":"BASKARANM@TITAN.CO.IN","level":"L5","dept":"BULLION MANAGEMENT","number":9965658011},
{"code":91858,"name":"RAJA S","email":"SRAJA@TITAN.CO.IN","level":"L3","dept":"CORPORATE SALES","number":0},
{"code":93574,"name":"MURALI J","email":"MURALIJ@TITAN.CO.IN","level":"5","dept":"SUPPLY CHAIN MANAGEMENT","number":9443325053},
{"code":94733,"name":"BALAKRISHNAN P","email":"BALAKRISHNANP@TITAN.CO.IN","level":"L5","dept":"FINANCE-EYEWEAR","number":9443776073},
{"code":96363,"name":"PRAKASH B S","email":"PRAKASHBS@TITAN.CO.IN","level":"L9","dept":"CORPORATE SUSTAINABILITY","number":9845903249},
{"code":96890,"name":"RAMESH RAO M","email":"RAMESHMRAO@TITAN.CO.IN","level":"L4","dept":"COO'S OFFICE-WATCH DIVISION","number":9443785113},
{"code":101944,"name":"PRADEEP PILLAI","email":"PRADEEP@TITAN.CO.IN","level":"L8","dept":"CORPORATE SALES","number":8025435833},
{"code":103660,"name":"MURUGAN G","email":"MURUGANG@TITAN.CO.IN","level":"L5","dept":"RETAILING-GOLD PLUS","number":9789778712},
{"code":107264,"name":"SUNDARARAJ V","email":"SUNDARRAJ@TITAN.CO.IN","level":"L7","dept":"CENTRAL TECHNOLOGY SERVICES","number":9443634096},
{"code":111319,"name":"SATHEESKUMAR T","email":"SATHEES@TITAN.CO.IN","level":"L5","dept":"SUPPLY CHAIN MANAGEMENT","number":9442528150},
{"code":117338,"name":"CHIDAMBARAM P","email":"CHIDAMBARAMP@TITAN.CO.IN","level":"L4","dept":"MARKETING-TITAN","number":9486015450},
{"code":120847,"name":"SHASHI MENON P","email":"SASHIMENON@TITAN.CO.IN","level":"L9","dept":"ADMINISTRATION","number":9845450140},
{"code":120933,"name":"AMARNAATH M K","email":"AMARNAATHMK@TITAN.CO.IN","level":"L5","dept":"INTERNAL AUDIT","number":8220255885},
{"code":129913,"name":"SARAVANAN P","email":"SARAVANAN@TITAN.CO.IN","level":"L4","dept":"SUPPLY CHAIN MANAGEMENT","number":4344245857},
{"code":138828,"name":"PREMKUMAR B","email":"PREMKUMAR@TITAN.CO.IN","level":"L5","dept":"SYSTEMS","number":9442185199},
{"code":151196,"name":"VAIDEESWARAN N","email":"VAIDEESHWARAN@TITAN.CO.IN","level":"L9","dept":"RETAILING-GOLD PLUS","number":9443285420},
{"code":158460,"name":"BHARATHAN K","email":"BHARATHANK@TITAN.CO.IN","level":"L6","dept":"RETAILING-TANISHQ","number":9443688212},
{"code":160982,"name":"NATARAJAN S","email":"NATARAJAN@TITAN.CO.IN","level":"L9","dept":"INTERNATIONAL OPERATIONS - TPD","number":9845650130},
{"code":161442,"name":"ARUNACHALAM S","email":"ARUNVASAM@TITAN.CO.IN","level":"L6","dept":"SYSTEMS","number":4344263188},
{"code":165573,"name":"RAJASEKAR A P","email":"RAJASEKARAP@TITAN.CO.IN","level":"L4","dept":"MARKETING-GOLD PLUS","number":0},
{"code":166904,"name":"SHANMUGASUNDARAM G","email":"SHANMUGAS@TITAN.CO.IN","level":"L5","dept":"MERCHANDISING-GOLD PLUS","number":9789778724},
{"code":173931,"name":"SRINIVASAN T S","email":"SRINIVASANTS@TITAN.CO.IN","level":"L4","dept":"JEWELLERY-FINANCE","number":9663888244},
{"code":174832,"name":"ANANTHAN S","email":"ANANDANS@TITAN.CO.IN","level":"L5","dept":"DESIGNS","number":9487668093},
{"code":176107,"name":"JAYARAJ V","email":"JAYARAJV@TITAN.CO.IN","level":"L3","dept":"SUPPLY CHAIN MANAGEMENT","number":9677066789},
{"code":179864,"name":"SHANMUGAM S","email":"SSHANMUGAM@TITAN.CO.IN","level":"L4","dept":"LEGAL","number":9003626270},
{"code":184820,"name":"SRINIVASAN K","email":"SRINIVASANK@TITAN.CO.IN","level":"L9","dept":"SYSTEMS","number":9443374208},
{"code":186009,"name":"JAYARAM M D","email":"JAYARAMM@TITAN.CO.IN","level":"L7","dept":"RETAILING-GOLD PLUS","number":9880717475},
{"code":186278,"name":"SATISH R","email":"SATISHR@TITAN.CO.IN","level":"L5","dept":"PURCHASE","number":8884809716},
{"code":189411,"name":"MOHAN RAO K","email":"MOHANRAOK@TITAN.CO.IN","level":"L5","dept":"PURCHASE","number":0},
{"code":192490,"name":"GNANASEKARAN P","email":"PGS@TITAN.CO.IN","level":"L4","dept":"FINANCE","number":9865112212},
{"code":194550,"name":"RAMESH C V","email":"RAMESHCV@TITAN.CO.IN","level":"L6","dept":"BULLION MANAGEMENT","number":0},
{"code":201933,"name":"VISHNU BHAT M","email":"VISHNUB@TITAN.CO.IN","level":"L6","dept":"FINANCE","number":0},
{"code":202662,"name":"GOPALARETHINAM B","email":"GOPALR@TITAN.CO.IN","level":"","dept":"FINANCE","number":9980138202},
{"code":203122,"name":"VENKATARAMAN C K","email":"VENKATCKV@TITAN.CO.IN","level":"CEO","dept":"GENERAL-TANISHQ","number":0},
{"code":206266,"name":"NARASIMHA MURTHY A","email":"NARASIMHAM@TITAN.CO.IN","level":"L5","dept":"CENTRAL TECHNOLOGY SERVICES","number":9844054129},
{"code":206438,"name":"THANKACHAN M J","email":"THANKACHAN@TITAN.CO.IN","level":"L6","dept":"INTERNATIONAL OPERATIONS - TPD","number":9243446797},
{"code":209668,"name":"AMARNATH C V","email":"AMARNATH@TITAN.CO.IN","level":"L8","dept":"CUSTOMER SERVICE DEPARTMENT","number":0},
{"code":212564,"name":"REVATHI KANT","email":"REVATHIK@TITAN.CO.IN","level":"AVP","dept":"DESIGNS-TANISHQ","number":9845114989},
{"code":215439,"name":"MADHAVAN S","email":"MADHAVANS@TITAN.CO.IN","level":"L6","dept":"E-COMMERCE GENERAL","number":9663158866},
{"code":217327,"name":"MADHAVA SHETTIGAR","email":"SHETTIGARM@TITAN.CO.IN","level":"L7","dept":"FINANCE","number":9448489179},
{"code":217854,"name":"THIRUMALMURUGUN S","email":"THIRUMALMURUGAN@TITAN.CO.IN","level":"L8","dept":"RETAIL PROJECTS","number":9243446792},
{"code":217940,"name":"JAYARAJ T","email":"JAYARAJT@TITAN.CO.IN","level":"L8","dept":"SYSTEMS","number":9900158655},
{"code":218927,"name":"SATHIAMOORTHY K","email":"SATHIAMOORTHY@TITAN.CO.IN","level":"L7","dept":"SYSTEMS","number":9629382550},
{"code":222466,"name":"MOHAMED FAROOK M J","email":"FAROOKM@TITAN.CO.IN","level":"L8","dept":"SUPPLY CHAIN MANAGEMENT","number":9845796910},
{"code":227057,"name":"JAGANNATH N","email":"JAGANNATHN@TITAN.CO.IN","level":"5","dept":"SUPPLY CHAIN AND LOGISTICS","number":0},
{"code":230738,"name":"LIZY SADASIVAN","email":"LIZYSA@TITAN.CO.IN","level":"L7","dept":"SYSTEMS","number":9972677883},
{"code":234697,"name":"SANKARANARAYANAN C S","email":"SANKARCS@TITAN.CO.IN","level":"L6","dept":"HUMAN RESOURCES","number":9880061482},
{"code":239105,"name":"PANNEER SELVAM C","email":"PANNEERSELVAMC@TITAN.CO.IN","level":"L9","dept":"MERCHANDISING-GOLD PLUS","number":9443279845},
{"code":239374,"name":"AJOY CHAWLA","email":"AJOYC@TITAN.CO.IN","level":"1","dept":"MD OFFICE","number":9845650118},
{"code":240382,"name":"SUBBA GANGA K","email":"SUBBAG@TITAN.CO.IN","level":"L8","dept":"SUPPLY CHAIN MANAGEMENT","number":9845101806},
{"code":242001,"name":"SHANTHI N","email":"SHANTHIN@TITAN.CO.IN","level":"L6","dept":"GENERAL-TANISHQ","number":9945988300},
{"code":244072,"name":"RAVI K N","email":"RAVIKN@TITAN.CO.IN","level":"L3","dept":"FINANCE","number":9731908811},
{"code":244685,"name":"JAIKRISHNAN R","email":"JAIKRISHNAN@TITAN.CO.IN","level":"L5","dept":"FINANCE","number":9482731499},
{"code":245059,"name":"SUDARSHAN C HEGDE","email":"HEGDE@TITAN.CO.IN","level":"L5","dept":"SYSTEMS","number":9632120088},
{"code":245930,"name":"RAMAN G","email":"GRAMAN@TITAN.CO.IN","level":"L6","dept":"SUPPLY CHAIN MANAGEMENT","number":9994306514},
{"code":248719,"name":"SRIDHAR N E","email":"SRIDHARNE@TITAN.CO.IN","level":"GM","dept":"CORPORATE SUSTAINABILITY","number":9243450116},
{"code":250284,"name":"PREMILA VAZ","email":"PREMILAV@TITAN.CO.IN","level":"L5","dept":"MD OFFICE","number":9448363543},
{"code":250370,"name":"MARY VERONICA","email":"MARYV@TITAN.CO.IN","level":"L4","dept":"FINANCE","number":0},
{"code":260186,"name":"GEORGE V L","email":"GEORGEVL@TITAN.CO.IN","level":"L7","dept":"FINANCE","number":9632222542},
{"code":260885,"name":"VEENA A","email":"VEENA@TITAN.CO.IN","level":"L4","dept":"FINANCE","number":9449342182},
{"code":263061,"name":"SREELATHA DINESH","email":"SREELATHAD@TITAN.CO.IN","level":"L5","dept":"PURCHASE","number":0},
{"code":263319,"name":"ARIF SALEEM PADIATH","email":"ARIFS@TITAN.CO.IN","level":"L8","dept":"MARKETING-ZOYA","number":0},
{"code":263846,"name":"GIRISON L","email":"GIRISON@TITAN.CO.IN","level":"L4","dept":"RETAILING-EYEWEAR","number":9035008050},
{"code":273221,"name":"GUGHA PRASAD K","email":"GUGHAP@TITAN.CO.IN","level":"L7","dept":"SUPPLY CHAIN MANAGEMENT","number":9442101166},
{"code":273834,"name":"PREMANAND S","email":"PREM@TITAN.CO.IN","level":"L7","dept":"SYSTEMS","number":9442577344},
{"code":276010,"name":"MURALIDHARA K R","email":"MURALIDHARA@TITAN.CO.IN","level":"L6","dept":"FINANCE","number":9448451602},
{"code":281676,"name":"SATISH S","email":"SATISHS@TITAN.CO.IN","level":"5","dept":"SALES-CERAMIC PRODUCTS","number":9970170456},
{"code":283478,"name":"ASHOK KUMAR MANE","email":"ASHOKKUMARM@TITAN.CO.IN","level":"L9","dept":"SALES-CSD","number":9731333467},
{"code":284551,"name":"SHREE RAM V","email":"SHREERAMV@TITAN.CO.IN","level":"L5","dept":"TRADE WATCHES","number":9900566595},
{"code":285011,"name":"NARAPPA REDDY H","email":"NARAPPAR@TITAN.CO.IN","level":"L6","dept":"COMMERCIAL","number":9900891191},
{"code":288854,"name":"SHANTHI DAVID","email":"SHANTHID@TITAN.CO.IN","level":"L6","dept":"FINANCE","number":9916043044},
{"code":294980,"name":"KISHORE R N","email":"RNKISHORE@TITAN.CO.IN","level":"L6","dept":"FINANCE","number":9845654547},
{"code":298315,"name":"AROKIA ANTHONY DASS S","email":"ANTHONY@TITAN.CO.IN","level":"L3","dept":"MARKETING-FASTRACK","number":9945359852},
{"code":298756,"name":"VIJAYAKUMAR N","email":"VIJAYAKUMARN@TITAN.CO.IN","level":"L4","dept":"ADMINISTRATION","number":9972094373},
{"code":300408,"name":"SARADH R","email":"SHARAD@TITAN.CO.IN","level":"5","dept":"RETAILING-EYEWEAR","number":9442266992},
{"code":301664,"name":"PRAHALLAD RS","email":"PRAHALLAD@TITAN.CO.IN","level":"L9","dept":"MERCHANDISING-HELIOS","number":9972016671},
{"code":304453,"name":"SURESH G","email":"SURESHG@TITAN.CO.IN","level":"L7","dept":"SUPPLY CHAIN MANAGEMENT","number":9443511589},
{"code":305795,"name":"RAVINDRA KUMAR M","email":"RAVINDRAK@TITAN.CO.IN","level":"L7","dept":"COMMERCIAL","number":9880187855},
{"code":306954,"name":"SUMANT SOOD","email":"SUMANT@TITAN.CO.IN","level":"L9","dept":"INNOVATION CENTRE","number":9243446793},
{"code":307769,"name":"ARUNA DEVI T","email":"ARUNADEVI@TITAN.CO.IN","level":"L5","dept":"MARKETING-TITAN","number":9945445265},
{"code":309130,"name":"ANILA J","email":"ANILAJ@TITAN.CO.IN","level":"L5","dept":"TRADE WATCHES","number":9844425117},
{"code":315170,"name":"THEKEVEEDU B ALEXANDER","email":"BIJUA@TITAN.CO.IN","level":"4","dept":"RETAILING-EYEWEAR","number":9845650128},
{"code":330383,"name":"SARAVANAN C","email":"CSARAVANAN@TITAN.CO.IN","level":"L6","dept":"DESIGNS","number":9894513140},
{"code":331897,"name":"MURALI KRISHNA N S","email":"MURALIKRISHNA@TITAN.CO.IN","level":"L5","dept":"MARKETING-TITAN","number":9845140160},
{"code":332443,"name":"MAHESH K B","email":"MAHESHKB@TITAN.CO.IN","level":"L4","dept":"ADMINISTRATION","number":9845555577},
{"code":337034,"name":"RAJENDRAN M","email":"RAJENDRAN@TITAN.CO.IN","level":"L4","dept":"MERCHANDISING-GOLD PLUS","number":9442210187},
{"code":339008,"name":"JAYASEELAN K","email":"JAYASEELANK@TITAN.CO.IN","level":"L5","dept":"RETAIL PROJECTS","number":9442424344},
{"code":347108,"name":"DEVARAJU M","email":"DEVARAJUM@TITAN.CO.IN","level":"L6","dept":"CUSTOMER SERVICE DEPARTMENT","number":919036000000},
{"code":348364,"name":"GANGADHARA A B","email":"GANGADHAR@TITAN.CO.IN","level":"L7","dept":"DESIGNS","number":9900654024},
{"code":349964,"name":"SHEKAR A","email":"SHEKARA@TITAN.CO.IN","level":"L5","dept":"FINANCE","number":0},
{"code":351959,"name":"RAMASUBRAMANIAM R","email":"RAMS@TITAN.CO.IN","level":"L8","dept":"SYSTEMS","number":4344291673},
{"code":353234,"name":"JEYAKUMAR J","email":"JEYAKUMAR@TITAN.CO.IN","level":"L5","dept":"SYSTEMS","number":9008333557},
{"code":355735,"name":"VADAKKEN D JOY","email":"JOY@TITAN.CO.IN","level":"L3","dept":"VISUAL MERCHANDISING-TANISHQ","number":9243459194},
{"code":356023,"name":"NARAHARI B L","email":"NARAHARI@TITAN.CO.IN","level":"L9","dept":"SYSTEMS","number":9845650133},
{"code":356464,"name":"BALASUBRAMANI V","email":"BALASUBRAMANI@TITAN.CO.IN","level":"L7","dept":"SYSTEMS","number":9894398233},
{"code":356722,"name":"RAMNATH M","email":"RAMNATHM@TITAN.CO.IN","level":"L7","dept":"SYSTEMS","number":9442544222},
{"code":357365,"name":"MAYIL VAGANAM K","email":"MAYIL@TITAN.CO.IN","level":"L5","dept":"RETAILING-TANISHQ","number":9901500665},
{"code":358879,"name":"SRIKANTH REDDY G","email":"SRIKANTHR@TITAN.CO.IN","level":"L5","dept":"SYSTEMS","number":9740433800},
{"code":360605,"name":"GOPALAKRISHNAN S","email":"GOPALAKRISHNANS@TITAN.CO.IN","level":"L4","dept":"MERCHANDISING-GOLD PLUS","number":9442261777},
{"code":361420,"name":"RAMACHANDRAN C","email":"RAMACHANDRANC@TITAN.CO.IN","level":"5","dept":"JEWELLERY-FINANCE","number":9845566899},
{"code":361775,"name":"GURURAJ H G","email":"GURU@TITAN.CO.IN","level":"L4","dept":"ECB","number":9845395735},
{"code":369241,"name":"PERUMAL G","email":"PERUMAL@TITAN.CO.IN","level":"L8","dept":"SYSTEMS","number":9880302476},
{"code":369768,"name":"ALAGAPPAN M","email":"ALAGAPPAN@TITAN.CO.IN","level":"L9","dept":"AFTER SALES SERVICE","number":9244545005},
{"code":372309,"name":"SOUNDARARAJAN M N","email":"SOUNDARMN@TITAN.CO.IN","level":"L9","dept":"SYSTEMS","number":9443325056},
{"code":376182,"name":"VIJAYANAND J","email":"VIJAYANAND@TITAN.CO.IN","level":"L5","dept":"SYSTEMS","number":9894996055},
{"code":376795,"name":"VIVEKANAND G","email":"VIVEKANAND@TITAN.CO.IN","level":"L5","dept":"SYSTEMS","number":9740127721},
{"code":378769,"name":"HEMCHANDER P N","email":"HEMCHANDER@TITAN.CO.IN","level":"L5","dept":"DESIGNS","number":0},
{"code":379670,"name":"ANANDAN V","email":"ANANDV@TITAN.CO.IN","level":"L5","dept":"PURCHASE","number":9843427778},
{"code":380678,"name":"VANILAKSHMI K R","email":"VANIK@TITAN.CO.IN","level":"L7","dept":"LEGAL","number":9243462483},
{"code":381052,"name":"MUNIRAJU N","email":"MUNIRAJU@TITAN.CO.IN","level":"L5","dept":"FINANCE","number":9243462483},
{"code":391567,"name":"KRISHNA KUMAR R","email":"KRISHNAK@TITAN.CO.IN","level":"L6","dept":"INTERNATIONAL OPERATIONS - TPD","number":9740375100},
{"code":392726,"name":"BALAJI S","email":"BALAJI@TITAN.CO.IN","level":"L4","dept":"MERCHANDISING-GOLD PLUS","number":9442110145},
{"code":394528,"name":"WALTER D SOUZA","email":"WALTERD@TITAN.CO.IN","level":"L5","dept":"MARKETING-FASTRACK","number":9844073372},
{"code":394883,"name":"MURUGANANDHAM C","email":"MURUGANANDHAM@TITAN.CO.IN","level":"L5","dept":"SYSTEMS","number":9443788136},
{"code":401825,"name":"KEERTHIVASAN S","email":"KEERTHIVASANS@TITAN.CO.IN","level":"L9","dept":"BULLION MANAGEMENT","number":9442514288},
{"code":402812,"name":"NAGANATH B S","email":"NAGANATH@TITAN.CO.IN","level":"L5","dept":"SYSTEMS","number":9448025315},
{"code":404442,"name":"BALAJI T K J","email":"BALAJITKJ@TITAN.CO.IN","level":"L5","dept":"JEWELLERY-FINANCE","number":9442254845},
{"code":404969,"name":"DAMODHARAN K R","email":"DAMODARAN@TITAN.CO.IN","level":"L5","dept":"SYSTEMS","number":7200087143},
{"code":405784,"name":"RAMACHANDRAN S S","email":"RAMACHANDRANSS@TITAN.CO.IN","level":"L4","dept":"MERCHANDISING-TANISHQ","number":9789133459},
{"code":405956,"name":"SAKTHIVEL S","email":"SAKTHIVELS@TITAN.CO.IN","level":"L5","dept":"RETAIL PROJECTS","number":9442532536},
{"code":408304,"name":"SAI USHA","email":"SAIUSHA@TITAN.CO.IN","level":"L4","dept":"MERCHANDISING-TANISHQ","number":9008818003},
{"code":408487,"name":"HARISH M K","email":"HARISHMK@TITAN.CO.IN","level":"L8","dept":"NEW BUSINESS DEVELOPMENT","number":9902111558},
{"code":408745,"name":"AVINASH KUMAR SRIVASTAVA","email":"AVINASH@TITAN.CO.IN","level":"L6","dept":"SUPPLY CHAIN MANAGEMENT","number":9901971638},
{"code":410127,"name":"VELMURUGAN P","email":"VELMURUGAN@TITAN.CO.IN","level":"L4","dept":"PURCHASE","number":9894455703},
{"code":410482,"name":"SARAVANAN R","email":"RSARAVANAN@TITAN.CO.IN","level":"L5","dept":"SUPPLY CHAIN MANAGEMENT","number":9611897445},
{"code":411727,"name":"SUNDARA VARDAN H E","email":"SUNDARAV@TITAN.CO.IN","level":"L7","dept":"RETAILING WATCHES","number":9845222304},
{"code":416673,"name":"PALANI T S","email":"PALANI@TITAN.CO.IN","level":"L4","dept":"MERCHANDISING-HELIOS","number":9008052721},
{"code":417832,"name":"SUDHAKAR GAMBIRAM","email":"SUDHAKARG@TITAN.CO.IN","level":"L5","dept":"RETAILING-GOLD PLUS","number":9789778714},
{"code":421102,"name":"SIDDURAJU S","email":"SIDDHUR@TITAN.CO.IN","level":"L7","dept":"SYSTEMS","number":9880302478},
{"code":421984,"name":"SHIVA KUMAR M A","email":"SHIVAK@TITAN.CO.IN","level":"L4","dept":"DESIGNS","number":9902581197},
{"code":422885,"name":"GURURAJA K V","email":"GURURAJAKV@TITAN.CO.IN","level":"L7","dept":"SYSTEMS","number":9448366382},
{"code":424074,"name":"SUNDARAM V","email":"SUNDARAMV@TITAN.CO.IN","level":"L4","dept":"SYSTEMS","number":9611100619},
{"code":424945,"name":"SOUNDARARAJAN S","email":"SOUNDARARAJAN@TITAN.CO.IN","level":"L7","dept":"PURCHASE","number":9845650155},
{"code":426661,"name":"KAMALADASS R","email":"KAMALADASS@TITAN.CO.IN","level":"L4","dept":"MERCHANDISING-TANISHQ","number":0},
{"code":427734,"name":"MOHAMED IDRIS A","email":"MIDRIS@TITAN.CO.IN","level":"L4","dept":"RETAILING-GOLD PLUS","number":8220000997},
{"code":427820,"name":"VIJAYA KUMAR B","email":"VIJAYAKUMAR@TITAN.CO.IN","level":"L4","dept":"RETAILING-GOLD PLUS","number":9994419797},
{"code":428990,"name":"SIVASELVAN V","email":"SIVASELVANV@TITAN.CO.IN","level":"L5","dept":"MERCHANDISING-TANISHQ","number":9677810610},
{"code":430103,"name":"SARAVANAN V","email":"SARAVANANV@TITAN.CO.IN","level":"L6","dept":"DESIGNS-TANISHQ","number":0},
{"code":431273,"name":"JAYARAMAN D L","email":"DLJAYARAMAN@TITAN.CO.IN","level":"L6","dept":"SYSTEMS","number":0},
{"code":431703,"name":"GURURAJA H","email":"GURURAJ@TITAN.CO.IN","level":"L5","dept":"SYSTEMS","number":0},
{"code":432088,"name":"KOORALLA SRINIVAS","email":"SRINIVASK@TITAN.CO.IN","level":"L8","dept":"SUPPLY CHAIN AND LOGISTICS","number":0},
{"code":438978,"name":"SATHISH B","email":"SATHISHB@TITAN.CO.IN","level":"L4","dept":"CORPORATE SALES","number":9944351009},
{"code":440274,"name":"SIVAGNANAM S","email":"SIVAGNANAM@TITAN.CO.IN","level":"L5","dept":"LARGE FORMAT STORES","number":8056430289},
{"code":444921,"name":"MUTHU PARAMASIVAM M","email":"MUTHUM@TITAN.CO.IN","level":"L4","dept":"FINANCE","number":8122619610},
{"code":448439,"name":"BALASUBRAMANIAM R","email":"BALASR@TITAN.CO.IN","level":"L4","dept":"FINANCE","number":9842928561},
{"code":453750,"name":"SULBIHAR ALI M","email":"SULBIHARALI@TITAN.CO.IN","level":"L5","dept":"JEWELLERY-FINANCE","number":9632223595},
{"code":455025,"name":"THIRUMURUGAN V","email":"THIRUMURUGAN@TITAN.CO.IN","level":"L6","dept":"RETAIL PROJECTS","number":9972966011},
{"code":455294,"name":"GANESH K P","email":"GANESHKP@TITAN.CO.IN","level":"L8","dept":"SYSTEMS","number":9442152388},
{"code":458427,"name":"SRIKALA K","email":"SRIKALAK@TITAN.CO.IN","level":"L5","dept":"FINANCE","number":9945082612},
{"code":458513,"name":"KANTHY C U","email":"KANTHY@TITAN.CO.IN","level":"L5","dept":"MERCHANDISING-TANISHQ","number":0},
{"code":459156,"name":"AYIL RAGHAVAN R","email":"AYIL@TITAN.CO.IN","level":"L5","dept":"VISUAL MERCHANDISING-TANISHQ","number":9894897474},
{"code":461592,"name":"JOSEPHINE ALLAN","email":"JOSEPHINEA@TITAN.CO.IN","level":"L4","dept":"INTEGRATED RETAIL SERVICES","number":9945133427},
{"code":462138,"name":"RAGHURAMAN R","email":"RAGHURAMANR@TITAN.CO.IN","level":"L5","dept":"SUPPLY CHAIN AND LOGISTICS","number":9741036002},
{"code":463394,"name":"BRINDA M","email":"BRINDA@TITAN.CO.IN","level":"L5","dept":"LEGAL","number":9902111335},
{"code":466097,"name":"VENKATESH R","email":"VENKATESHR@TITAN.CO.IN","level":"L8","dept":"SYSTEMS","number":9880061729},
{"code":466269,"name":"SREEKANTH M","email":"SREEKANTH@TITAN.CO.IN","level":"L6","dept":"JEWELLERY-FINANCE","number":919442000000},
{"code":466796,"name":"DAVINDER K SETHI","email":"SETHI@TITAN.CO.IN","level":"L6","dept":"HUMAN RESOURCES","number":0},
{"code":467428,"name":"DEEBAC P","email":"DEEBACP@TITAN.CO.IN","level":"L4","dept":"PURCHASE","number":9894175825},
{"code":470851,"name":"SENTHIL KUMAR U","email":"SENTHILKUMARU@TITAN.CO.IN","level":"L4","dept":"HUMAN RESOURCES","number":9047494935},
{"code":471752,"name":"VINOTH C","email":"VINOTHC@TITAN.CO.IN","level":"L4","dept":"SYSTEMS","number":8066609660},
{"code":474014,"name":"SARAVANAN R","email":"SARAVANANR@TITAN.CO.IN","level":"L4","dept":"MERCHANDISING-TANISHQ","number":9843998890},
{"code":475356,"name":"RAJA R","email":"RAJAR@TITAN.CO.IN","level":"L6","dept":"SUPPLY CHAIN MANAGEMENT","number":9442925931},
{"code":476085,"name":"NATARAJ V","email":"NATARAJ@TITAN.CO.IN","level":"L6","dept":"SYSTEMS","number":9632104411},
{"code":477857,"name":"NEIL FOLEY","email":"NEILFOLEY@TITAN.CO.IN","level":"L9","dept":"MARKETING-TITAN","number":0},
{"code":478317,"name":"RATHISH S","email":"RATHISHS@TITAN.CO.IN","level":"L8","dept":"RETAIL PROJECTS","number":9442121300},
{"code":484185,"name":"BALA KUMAR E","email":"BALAK@TITAN.CO.IN","level":"L6","dept":"JEWELLERY-FINANCE","number":0},
{"code":485516,"name":"GANESHA","email":"GANESHA@TITAN.CO.IN","level":"L6","dept":"FINANCE","number":9535076339},
{"code":485602,"name":"SHASHIKANTH C A","email":"SHASHIKANTH@TITAN.CO.IN","level":"L5","dept":"FINANCE","number":9844331660},
{"code":490655,"name":"SRIKANTH MURTHY","email":"SRIKANTHM@TITAN.CO.IN","level":"L6","dept":"CUSTOMER SERVICE DEPARTMENT","number":9900061488},
{"code":495687,"name":"JANARDHANA PAI","email":"PAI@TITAN.CO.IN","level":"L7","dept":"FINANCE","number":9845545953},
{"code":496233,"name":"KRISHNAMOORTHI K","email":"KRISHNAMOORTHIK@TITAN.CO.IN","level":"L7","dept":"MERCHANDISING - WAD","number":8242481950},
{"code":496674,"name":"RADHAKRISHNAN P R","email":"RADHAPR@TITAN.CO.IN","level":"5","dept":"SYSTEMS","number":9443325046},
{"code":498734,"name":"CHANDRA KUMAR N","email":"CHANDRAK@TITAN.CO.IN","level":"L8","dept":"SYSTEMS","number":9845341780},
{"code":499022,"name":"ASHIS OBEDANAND","email":"ASHISH@TITAN.CO.IN","level":"L7","dept":"SYSTEMS","number":9845944324},
{"code":505160,"name":"SRIDHARA H S","email":"HSSRIDHARA@TITAN.CO.IN","level":"L6","dept":"FINANCE-EYEWEAR","number":9611106448},
{"code":510643,"name":"PUGAZHAENDHI P","email":"PUGALP@TITAN.CO.IN","level":"L6","dept":"RETAIL PROJECTS","number":9442648030},
{"code":511017,"name":"RAVEESH H S","email":"RAVEESH@TITAN.CO.IN","level":"L7","dept":"DESIGNS","number":9900219386},
{"code":513873,"name":"NIRMAL I LOBO","email":"NIRMALL@TITAN.CO.IN","level":"L9","dept":"RETAILING WATCHES","number":9880870025},
{"code":519978,"name":"YASHWANTH KUMAR C","email":"YASHWANTHK@TITAN.CO.IN","level":"L9","dept":"Consumer Insights & Analytics","number":9243446799},
{"code":520631,"name":"ARUN NARAYAN","email":"ARUN@TITAN.CO.IN","level":"4","dept":"GENERAL-HELIOS","number":9880260969},
{"code":521532,"name":"JOSEPH PRINCE C K","email":"JOSEPHPRINCE@TITAN.CO.IN","level":"L7","dept":"FRAGRANCES-SALES","number":918026000000},
{"code":522874,"name":"BHISHEN SINGH DABOLA","email":"COMMUNICATION@TITAN.CO.IN","level":"L3","dept":"ADMINISTRATION","number":9035466452},
{"code":525136,"name":"SOMPRABH KUMAR SINGH","email":"SOMPRABH@TITAN.CO.IN","level":"L9","dept":"DESIGNS","number":9972028432},
{"code":527637,"name":"SATHYANARAYANA MARAKINI","email":"MARAKINISN@TITAN.CO.IN","level":"L9","dept":"SYSTEMS","number":8065624899},
{"code":528194,"name":"BALAJI NATARAJAN","email":"BALAJIN@TITAN.CO.IN","level":"L9","dept":"VISUAL MERCHANDISING-TANISHQ","number":9243462488},
{"code":531606,"name":"PREMA KUMAR M","email":"PREMAK@TITAN.CO.IN","level":"L7","dept":"SYSTEMS","number":9945512542},
{"code":536552,"name":"SUKANYA GOPINATH","email":"SUKANYAG@TITAN.CO.IN","level":"L8","dept":"VISUAL MERCHANDISING-TANISHQ","number":9243474241},
{"code":537281,"name":"VIJESH RAJAN","email":"VIJESH@TITAN.CO.IN","level":"5","dept":"INTERNATIONAL OPERATIONS - TPD","number":9845748533},
{"code":541508,"name":"BHARAT JHAVERI","email":"BHARATJ@TITAN.CO.IN","level":"L8","dept":"MERCHANDISING-TANISHQ","number":9739004894},
{"code":541691,"name":"PARESH RASTOGI","email":"PARESH@TITAN.CO.IN","level":"L7","dept":"LARGE FORMAT STORES","number":9674033363},
{"code":542764,"name":"DURAIRAJ C R","email":"DURAIRAJ@TITAN.CO.IN","level":"L8","dept":"SAFETY","number":9442646025},
{"code":544566,"name":"AMIT V KULKARNI","email":"AMITK@TITAN.CO.IN","level":"L6","dept":"SYSTEMS","number":8197989900},
{"code":561054,"name":"YOGESH M APHALE","email":"YOGESHAPHALE@TITAN.CO.IN","level":"L8","dept":"SUPPLY CHAIN AND LOGISTICS","number":8065727051},
{"code":564456,"name":"KANCHAN ROY","email":"KANCHANR@TITAN.CO.IN","level":"L7","dept":"SYSTEMS","number":9902477334},
{"code":564897,"name":"DINESH AMITHA","email":"DINESHA@TITAN.CO.IN","level":"L9","dept":"MARKETING-ACCESSORIES","number":9845650122},
{"code":565271,"name":"AJAY POONOLLY","email":"AJAYP@TITAN.CO.IN","level":"L6","dept":"INTERNATIONAL OPERATIONS - TPD","number":9900443620},
{"code":565443,"name":"ADITYA KEJRIWAL","email":"ADITYAK@TITAN.CO.IN","level":"L8","dept":"MARKETING-HELIOS","number":9980197797},
{"code":565529,"name":"SUNIL RAJ","email":"SUNILR@TITAN.CO.IN","level":"L9","dept":"MERCHANDISING-TANISHQ","number":0},
{"code":565701,"name":"SHRUTI MALA","email":"SHRUTIM@TITAN.CO.IN","level":"L7","dept":"NEW BUSINESS DEVELOPMENT","number":9243474244},
{"code":569219,"name":"NIRAJ GANPATRAO BHAKARE","email":"NIRAJ@TITAN.CO.IN","level":"L9","dept":"MERCHANDISING-TANISHQ","number":9223204300},
{"code":572814,"name":"SHALINI GUPTA","email":"SHALINIG@TITAN.CO.IN","level":"L9","dept":"MARKETING-SONATA","number":9845161125},
{"code":574971,"name":"AJAY DWIVEDI","email":"AJAYD@TITAN.CO.IN","level":"L8","dept":"LARGE FORMAT STORES","number":9880544335},
{"code":577061,"name":"SHYAMALA RAMANAN","email":"SHYAMALAR@TITAN.CO.IN","level":"L9","dept":"MARKETING-FAVRE LEUBA","number":9845158567},
{"code":580656,"name":"MEDHA NAIK","email":"MEDHA@TITAN.CO.IN","level":"L7","dept":"MERCHANDISING-TANISHQ","number":9845325670},
{"code":582372,"name":"RAJVEER SINGH GREWAL","email":"RAJVEERG@TITAN.CO.IN","level":"L7","dept":"INTERNATIONAL OPERATIONS - TPD","number":0},
{"code":582630,"name":"VANDANA BHALLA","email":"VANDANAB@TITAN.CO.IN","level":"L9","dept":"MARKETING EYEWEAR","number":9845196902},
{"code":582985,"name":"SHESHA SIMHAN N","email":"SHESHAS@TITAN.CO.IN","level":"L5","dept":"ADMINISTRATION","number":9674389054},
{"code":583273,"name":"HEMAL PANCHAMIA","email":"HEMALP@TITAN.CO.IN","level":"L8","dept":"MARKETING-FASTRACK","number":0},
{"code":593347,"name":"SANJAY BHATTACHARJEE","email":"SANJAYB@TITAN.CO.IN","level":"L8","dept":"RETAILING WATCHES","number":0},
{"code":593788,"name":"CHITTI BABU G","email":"CHITTIB@TITAN.CO.IN","level":"L8","dept":"VISUAL MERCHANDISING-TANISHQ","number":0},
{"code":594162,"name":"GANESAN S","email":"GANESANS@TITAN.CO.IN","level":"L4","dept":"DESIGNS","number":9003930612},
{"code":595934,"name":"GIRI K","email":"GIRIK@TITAN.CO.IN","level":"L6","dept":"SYSTEMS","number":9894177218},
{"code":603788,"name":"SIRISH CHANDRASHEKAR","email":"SIRISHC@TITAN.CO.IN","level":"L9","dept":"MARKETING-TITAN","number":0},
{"code":604076,"name":"RAJDEEP SARKAR","email":"RAJDEEP@TITAN.CO.IN","level":"L6","dept":"MERCHANDISING-TANISHQ","number":9972737783},
{"code":604248,"name":"PIYUSH SETH","email":"PIYUSHS@TITAN.CO.IN","level":"L7","dept":"MARKETING-TITAN","number":9008004270},
{"code":604420,"name":"ABHIJEET TIWARY","email":"ABHIJEET@TITAN.CO.IN","level":"L7","dept":"INTERNATIONAL OPERATIONS - TPD","number":96417766},
{"code":605848,"name":"SRIRAMAGURU G","email":"SRIRAMAGURU@TITAN.CO.IN","level":"L5","dept":"SYSTEMS","number":7708004847},
{"code":608024,"name":"KATHIRAVAN P M","email":"KATHIR@TITAN.CO.IN","level":"L6","dept":"SYSTEMS","number":9845406695},
{"code":608293,"name":"SUPARNA DAPKE","email":"SUPARNA@TITAN.CO.IN","level":"D4","dept":"DESIGNS","number":9632140837},
{"code":608551,"name":"GURURAJA HEBBAR","email":"GURURAJA@TITAN.CO.IN","level":"L5","dept":"BULLION MANAGEMENT","number":9663044005},
{"code":610105,"name":"SURESH R","email":"SURESHR@TITAN.CO.IN","level":"L9","dept":"MD OFFICE","number":9880501255},
{"code":619795,"name":"RAHUL BOHRE","email":"RAHULB@TITAN.CO.IN","level":"L6","dept":"SALES-TANISHQ","number":9900249028},
{"code":623936,"name":"KALPANA RANGAMANI","email":"KALPANA@TITAN.CO.IN","level":"","dept":"FRAGRANCES-SALES","number":0},
{"code":628269,"name":"SWAROOPA M V","email":"SWAROOPAM@TITAN.CO.IN","level":"L5","dept":"FINANCE","number":9900428002},
{"code":629256,"name":"KRISHNAMURTHI T V","email":"KRISHNAMURTHI@TITAN.CO.IN","level":"L9","dept":"HUMAN RESOURCES","number":9945516568},
{"code":631165,"name":"WASEEM KARIM","email":"WASEEMK@TITAN.CO.IN","level":"L7","dept":"MERCHANDISING-HELIOS","number":9945691185},
{"code":632066,"name":"VASANTHA NARAYAN","email":"VASANTHA@TITAN.CO.IN","level":"L5","dept":"COO'S OFFICE-WATCH DIVISION","number":9902771541},
{"code":637442,"name":"SHIBADITYA GHOSH","email":"SHIBADITYA@TITAN.CO.IN","level":"L9","dept":"FINANCE","number":9830009306},
{"code":640693,"name":"SIVASHANKER A","email":"SIVAS@TITAN.CO.IN","level":"L4","dept":"DESIGNS","number":9003687007},
{"code":640951,"name":"ANAND YOGI","email":"ANANDY@TITAN.CO.IN","level":"L6","dept":"DESIGNS","number":0},
{"code":644297,"name":"RAJESH YK","email":"RAJESHYK@TITAN.CO.IN","level":"L7","dept":"FINANCE","number":9448054828},
{"code":644996,"name":"BALASAHEB DHANSINGH MHASKE","email":"BALASAHEB@TITAN.CO.IN","level":"L8","dept":"GENERAL-EYEWEAR","number":9945694644},
{"code":646701,"name":"PRASATH K","email":"PRASATHK@TITAN.CO.IN","level":"L4","dept":"MERCHANDISING-TANISHQ","number":9035351180},
{"code":649146,"name":"MAHENDRA PRATAP SINGH CHAUHAN","email":"MAHENDRA@TITAN.CO.IN","level":"D5","dept":"DESIGNS","number":0},
{"code":649931,"name":"SUBISH SUDHAKARAN","email":"SUBISH@TITAN.CO.IN","level":"L7","dept":"MARKETING-TITAN","number":0},
{"code":651926,"name":"JOE CHACKO","email":"JOECHACKO@TITAN.CO.IN","level":"GM","dept":"HUMAN RESOURCES","number":9980532912},
{"code":653384,"name":"JAMES SELVARAJ R","email":"JAMESS@TITAN.CO.IN","level":"L5","dept":"SYSTEMS","number":8123921262},
{"code":653997,"name":"DINESH S","email":"SDINESH@TITAN.CO.IN","level":"L6","dept":"RETAIL PROJECTS","number":9442210419},
{"code":654016,"name":"VENKATA SUBRAMANIAM R","email":"VENKATASUBRAMANIAMR@TITAN.CO.IN","level":"L6","dept":"SYSTEMS","number":9894259444},
{"code":654629,"name":"RAJ BAHADUR","email":"RBCHAURASIA@TITAN.CO.IN","level":"L5","dept":"MARKETING-ZOYA","number":9740980123},
{"code":655186,"name":"ASHUTOSH KUMAR","email":"ASHUTOSH@TITAN.CO.IN","level":"L5","dept":"MERCHANDISING-TANISHQ","number":9611114782},
{"code":655971,"name":"VASUDEVA RAO D","email":"VASUDEVA@TITAN.CO.IN","level":"L7","dept":"MERCHANDISING-GOLD PLUS","number":9442269777},
{"code":658674,"name":"AROGHYA GODWIN K","email":"KAGODWIN@TITAN.CO.IN","level":"L4","dept":"E-COMMERCE GENERAL","number":9741414164},
{"code":664187,"name":"RAKESH P","email":"RAKESHP@TITAN.CO.IN","level":"L4","dept":"FINANCE","number":9916888151},
{"code":664445,"name":"ELANGOVAN R N","email":"ELANGOVANRN@TITAN.CO.IN","level":"L9","dept":"HUMAN RESOURCES","number":9442266825},
{"code":669208,"name":"SANTOSH G N","email":"SANTOSHGN@TITAN.CO.IN","level":"L6","dept":"MERCHANDISING-TANISHQ","number":9845212471},
{"code":673005,"name":"GAURAV KALA","email":"GAURAV@TITAN.CO.IN","level":"L9","dept":"RETAILING-HELIOS","number":0},
{"code":673274,"name":"ATUL JADHAM","email":"ATULJ@TITAN.CO.IN","level":"L6","dept":"MERCHANDISING-TANISHQ","number":0},
{"code":675947,"name":"MUTHUSAMY A","email":"MUTHUSAMYA@TITANWORLD.COM","level":"L5","dept":"BUSINESS DEVELOPMENT-IRSG","number":9150309325},
{"code":676848,"name":"KARTHICK C","email":"KARTHICKC@TITAN.CO.IN","level":"L6","dept":"MERCHANDISING-GOLD PLUS","number":9600261786},
{"code":680473,"name":"KARTHICK V","email":"KARTHICKV@TITAN.CO.IN","level":"L5","dept":"SUPPLY CHAIN AND LOGISTICS","number":9880124666},
{"code":681632,"name":"SHIV SHANKAR KUMAR","email":"SHIVSHANKAR@TITAN.CO.IN","level":"L6","dept":"SYSTEMS","number":8292501920},
{"code":681987,"name":"BIDYUT NATH","email":"BIDYUT@TITAN.CO.IN","level":"L9","dept":"CUSTOMER LOYALTY AND ANALYTICS","number":0},
{"code":682361,"name":"AJAY H SHARMA","email":"AJAYSHARMA@TITAN.CO.IN","level":"4","dept":"INTERNAL AUDIT","number":9740509491},
{"code":683090,"name":"SEETHAMMA","email":"SEETHAMMA@TITAN.CO.IN","level":"L4","dept":"PEW-QUALITY","number":8274201030},
{"code":683176,"name":"NARESH G NAIR","email":"NARESHGN@TITAN.CO.IN","level":"L6","dept":"CORPORATE SALES","number":9900244088},
{"code":683262,"name":"DILIP KUMAR D","email":"DILIPK@TITAN.CO.IN","level":"L4","dept":"SUPPLY CHAIN AND LOGISTICS","number":0},
{"code":685849,"name":"SATHISH KUMAR D","email":"SATHISHKUMARD@TITAN.CO.IN","level":"L4","dept":"SYSTEMS","number":8088330555},
{"code":686664,"name":"VENKATESAN S","email":"VENKATS@TITAN.CO.IN","level":"L5","dept":"SYSTEMS","number":9880371719},
{"code":687479,"name":"MURUGAN S","email":"MURUGANS@TITAN.CO.IN","level":"L8","dept":"RETAIL PROJECTS","number":9972733552},
{"code":687565,"name":"SANGEETHA V PILLAI","email":"SANGEETHAP@TITAN.CO.IN","level":"L5","dept":"RETAILING-TANISHQ","number":9243495635},
{"code":688552,"name":"VENKATESAN G","email":"GVENKATESAN@TITAN.CO.IN","level":"L5","dept":"SYSTEMS","number":9591791180},
{"code":688724,"name":"MANAS CHITRAKAR","email":"MANAS@TITAN.CO.IN","level":"D2","dept":"DESIGNS-TANISHQ","number":9488750455},
{"code":688993,"name":"VINAYAKA BHAT","email":"VINAYAKA@TITAN.CO.IN","level":"L9","dept":"PEW-QUALITY","number":8386268314},
{"code":689894,"name":"SARAVANA S","email":"SARAVANAS@TITAN.CO.IN","level":"L4","dept":"FINANCE-EYEWEAR","number":9886616957},
{"code":690375,"name":"ABHISHEK RASTOGI","email":"ABHISHEKR@TITAN.CO.IN","level":"D5","dept":"DESIGNS-TANISHQ","number":9916391250},
{"code":690633,"name":"DEEPALI KRISHNARAO SHIRKE","email":"DEEPALI@TITAN.CO.IN","level":"L4","dept":"HUMAN RESOURCES","number":9739983938},
{"code":691362,"name":"RAJESH C","email":"RAJESHC@TITAN.CO.IN","level":"L6","dept":"JEWELLERY-FINANCE","number":0},
{"code":692435,"name":"SANTHI P S","email":"SANTHIP@TITAN.CO.IN","level":"L3","dept":"CORPORATE SUSTAINABILITY","number":9442200567},
{"code":693508,"name":"POOJA KABRA","email":"POOJA@TITAN.CO.IN","level":"D3","dept":"DESIGNS-TANISHQ","number":9916138637},
{"code":693777,"name":"VIMALRAJ A M","email":"VIMALR@TITAN.CO.IN","level":"L7","dept":"FINANCE","number":9980339034},
{"code":694323,"name":"VARUN P","email":"VARUN@TITAN.CO.IN","level":"L3","dept":"FINANCE","number":9036262825},
{"code":695138,"name":"TEENA SEBASTIAN","email":"TEENA@TITAN.CO.IN","level":"L6","dept":"SYSTEMS","number":9686485878},
{"code":695837,"name":"SIVARAMA KRISHNAN S","email":"SIVARAMAKRISHNANS@TITAN.CO.IN","level":"L6","dept":"SYSTEMS","number":9442233773},
{"code":695923,"name":"SMRITI RANJAN BANDYOPADHYAY","email":"SMRITIR@TITAN.CO.IN","level":"L4","dept":"DESIGNS-TANISHQ","number":9844063361},
{"code":699269,"name":"BALAJI P","email":"PBALAJI@TITAN.CO.IN","level":"L4","dept":"MERCHANDISING-HELIOS","number":8123461145},
{"code":699613,"name":"SARITA FERNANDES","email":"SARITA@TITAN.CO.IN","level":"L3","dept":"ADMINISTRATION","number":8050575540},
{"code":700289,"name":"KRUPESHA M","email":"KRUPESHAM@TITAN.CO.IN","level":"L5","dept":"DESIGNS","number":9731899577},
{"code":701276,"name":"RAVIKANTH G","email":"RAVIKANTH@TITAN.CO.IN","level":"L5","dept":"MERCHANDISING-GOLD PLUS","number":9701705860},
{"code":701706,"name":"UDHAYA KUMAR G","email":"UDHAYA@TITAN.CO.IN","level":"L6","dept":"RETAILING-GOLD PLUS","number":9789778717},
{"code":706125,"name":"VIKRAM V MUKTI","email":"VIKRAMV@TITAN.CO.IN","level":"L4","dept":"FINANCE","number":9844176937},
{"code":706652,"name":"AMALA RANJAN","email":"AMALA@TITAN.CO.IN","level":"L4","dept":"SYSTEMS","number":9035568092},
{"code":713765,"name":"SRIDHAR K S","email":"SRIDHARKS@TITAN.CO.IN","level":"L8","dept":"HUMAN RESOURCES","number":9972366851},
{"code":714666,"name":"VISHAL BHATNAGAR","email":"VISHALB@TITAN.CO.IN","level":"D3","dept":"DESIGNS","number":9980052782},
{"code":715040,"name":"NAVEEN SUHAS CRASTA","email":"NAVEENCRASTA@TITAN.CO.IN","level":"L6","dept":"SYSTEMS","number":9900569543},
{"code":715911,"name":"JAHNAVI JOSHI","email":"JAHNAVI@TITAN.CO.IN","level":"L4","dept":"DESIGNS-TANISHQ","number":8792383155},
{"code":717627,"name":"ADITYA GOVIND GADIYAR","email":"ADITYAG@TITAN.CO.IN","level":"L7","dept":"MARKETING-TANISHQ","number":0},
{"code":718001,"name":"BHUVNESH JAIN","email":"BHUVNESH@TITAN.CO.IN","level":"L7","dept":"MERCHANDISING-TANISHQ","number":8939969101},
{"code":720964,"name":"RAJAVEL K","email":"RAJAVELK@TITAN.CO.IN","level":"L4","dept":"FINANCE","number":8526093442},
{"code":722239,"name":"DEEKSHA SATISH SHETTY","email":"DEEKSHAS@TITAN.CO.IN","level":"L5","dept":"DESIGNS-TANISHQ","number":9880656162},
{"code":722325,"name":"KARTHIKEYAN R","email":"KARTHIKR@TITAN.CO.IN","level":"L6","dept":"LEGAL","number":9489966716},
{"code":722594,"name":"SRINIVASA NAIK K","email":"SRINIVASANAIK@TITAN.CO.IN","level":"L5","dept":"DESIGNS-TANISHQ","number":9844507006},
{"code":725469,"name":"TAMILARASAN S","email":"TAMILARASAN@TITAN.CO.IN","level":"L5","dept":"SYSTEMS","number":9894336329},
{"code":729159,"name":"SREENATH M","email":"SREENATH@TITAN.CO.IN","level":"L3","dept":"PURCHASE","number":9741611007},
{"code":731154,"name":"GANESH KUMAR B","email":"GANESHKUMARB@TITAN.CO.IN","level":"L6","dept":"SYSTEMS","number":99722246932},
{"code":734997,"name":"SUNKARA JYOTHEE SWAROOP","email":"JYOTHEES@TITAN.CO.IN","level":"L8","dept":"SUPPLY CHAIN AND LOGISTICS","number":9900891784},
{"code":735102,"name":"DEEPAK AGARWAL","email":"DAGRAWAL@TITAN.CO.IN","level":"L9","dept":"COMMERCIAL","number":0},
{"code":735285,"name":"SANIL DHADWAL","email":"SANIL@TITAN.CO.IN","level":"D3","dept":"DESIGNS","number":9945299885},
{"code":737431,"name":"MOUSUMI DAS","email":"MOUSUMI@TITAN.CO.IN","level":"L4","dept":"GENERAL-EYEWEAR","number":8197398182},
{"code":743815,"name":"UTKARSH THAKUR","email":"UTKARSHT@TITAN.CO.IN","level":"L8","dept":"INTERNATIONAL OPERATIONS - TPD","number":9740030885},
{"code":745703,"name":"SANTOSH KUMAR M","email":"SANTHOSHM@TITAN.CO.IN","level":"L4","dept":"RETAILING WATCHES","number":9980999557},
{"code":747333,"name":"GOVINDARAJAN VASUDEVA RAO","email":"VASU@TITAN.CO.IN","level":"L5","dept":"SYSTEMS","number":9000203101},
{"code":751829,"name":"MANJUNATH R","email":"MANJU@TITAN.CO.IN","level":"L4","dept":"PURCHASE","number":9611126767},
{"code":754887,"name":"PRASHANTH K","email":"PRASHANTHK@TITAN.CO.IN","level":"L4","dept":"FINANCE","number":9844374305},
{"code":755175,"name":"VIJAY PRASAD","email":"VIJAYPRASAD@TITAN.CO.IN","level":"L5","dept":"RETAILING-GOLD PLUS","number":8861600005},
{"code":756334,"name":"SOMASHEKAR M S","email":"SOMASHEKARMS@TITAN.CO.IN","level":"L5","dept":"DESIGNS-EYEWEAR","number":0},
{"code":757590,"name":"SURESH N","email":"SURESHN@TITAN.CO.IN","level":"L4","dept":"FINANCE","number":9036240500},
{"code":764348,"name":"PRASANNA KUMAR P S","email":"PRASANNA.K@TITAN.CO.IN","level":"L5","dept":"MERCHANDISING-GOLD PLUS","number":9902100115},
{"code":767922,"name":"VINOD MANNAVA","email":"VINODMANNAVA@TITAN.CO.IN","level":"L5","dept":"MERCHANDISING-HELIOS","number":9448296357},
{"code":768565,"name":"SHATABDI SANGEETA","email":"SHATABDIS@TITAN.CO.IN","level":"D3","dept":"DESIGNS","number":9740333772},
{"code":769025,"name":"AJAY KUMAR B V","email":"AJAY@TITAN.CO.IN","level":"L7","dept":"VISUAL MERCHANDISING-TANISHQ","number":0},
{"code":769294,"name":"SUMIT PRAKASH","email":"SUMITPRAKASH@TITAN.CO.IN","level":"D3","dept":"DESIGNS","number":0},
{"code":770646,"name":"SANOBER MANNAN","email":"SANOBER@TITAN.CO.IN","level":"L7","dept":"MARKETING-TANISHQ","number":9886119834},
{"code":772190,"name":"NIDHI GUPTA","email":"NIDHIG@TITAN.CO.IN","level":"D2","dept":"DESIGNS","number":0},
{"code":772620,"name":"SANKAR Y","email":"SANKARY@TITAN.CO.IN","level":"L8","dept":"HUMAN RESOURCES","number":9663384385},
{"code":782963,"name":"AYUSHMAN CHIRANEWALA","email":"AYUSHMANC@TITAN.CO.IN","level":"L7","dept":"INTERNATIONAL OPERATIONS - TPD","number":9986337270},
{"code":787027,"name":"DINESH KUMAR C","email":"DINESHKUMARC@TITAN.CO.IN","level":"L5","dept":"SUPPLY CHAIN AND LOGISTICS","number":8050006406},
{"code":793594,"name":"SUNIL HAJERI","email":"SUNILH@TITAN.CO.IN","level":"L5","dept":"CENTRAL TECHNOLOGY SERVICES","number":9986465337},
{"code":799871,"name":"ARUL RAJ S","email":"ARULS@TITAN.CO.IN","level":"L6","dept":"RETAILING-TANISHQ","number":9880608912},
{"code":800891,"name":"RAMESH PILLAI","email":"RAMESHP@TITAN.CO.IN","level":"L8","dept":"GENERAL-EYEWEAR","number":9008699220},
{"code":808271,"name":"POORNIMA R","email":"POORNIMA@TITAN.CO.IN","level":"L4","dept":"SYSTEMS","number":9945129216},
{"code":809344,"name":"VINAY B L","email":"VINAYBL@TITAN.CO.IN","level":"L4","dept":"FINANCE","number":8095669649},
{"code":809430,"name":"ACHYUT J MURNAL","email":"ACHYUTM@TITAN.CO.IN","level":"L4","dept":"FINANCE","number":9611569124},
{"code":809957,"name":"HILDA MENEZES","email":"HILDA@TITAN.CO.IN","level":"L5","dept":"GENERAL-EYEWEAR","number":9886629803},
{"code":811081,"name":"ANANDA S","email":"SANAND@TITAN.CO.IN","level":"L3","dept":"JEWELLERY-FINANCE","number":9164778811},
{"code":811253,"name":"HEMANTH KUMAR V","email":"HEMANTHK@TITAN.CO.IN","level":"L5","dept":"COMMERCIAL","number":9611255335},
{"code":816102,"name":"RAVIKUMAR B","email":"RAVIKUMARB@TITAN.CO.IN","level":"L5","dept":"PEW-QUALITY","number":9886072037},
{"code":823129,"name":"SREENIVASA BABU P G","email":"SREENIVASAPG@TITANWORLD.COM","level":"L5","dept":"JEWELLERY-FINANCE","number":9731855221},
{"code":824643,"name":"SHALINI LING KUMAR","email":"SHALINIL@TITAN.CO.IN","level":"L4","dept":"AFTER SALES SERVICE","number":0},
{"code":826004,"name":"JAVED K M","email":"JAVED@TITAN.CO.IN","level":"L8","dept":"RETAILING-EYEWEAR","number":9611103870},
{"code":826972,"name":"KARTHIKEYAN M","email":"KARTHIKEYANM@TITAN.CO.IN","level":"L6","dept":"ADMINISTRATION","number":9986273819},
{"code":827346,"name":"BALAJI DAMODARAN","email":"BALAJID@TITAN.CO.IN","level":"L5","dept":"SUPPLY CHAIN AND LOGISTICS","number":8088360064},
{"code":829847,"name":"HEMANT PAL","email":"HEMANTPAL@TITAN.CO.IN","level":"D4","dept":"DESIGNS","number":9663111882},
{"code":831143,"name":"RITIKA GANDHI","email":"RITIKA@TITAN.CO.IN","level":"L6","dept":"CORPORATE SUSTAINABILITY","number":9845439605},
{"code":831670,"name":"PALLAVI BHAT","email":"PALLAVIB@TITAN.CO.IN","level":"L7","dept":"HUMAN RESOURCES","number":9632769697},
{"code":832044,"name":"NIRAJ PRASAD","email":"NIRAJPRASAD@TITAN.CO.IN","level":"L5","dept":"SYSTEMS","number":8147472044},
{"code":833031,"name":"GOUTAM JARTARGHAR","email":"GOUTAMJ@TITAN.CO.IN","level":"L3","dept":"FINANCE","number":9743896910},
{"code":833117,"name":"SUJAY SURESH DANGI","email":"SUJAYSDANGI@TITAN.CO.IN","level":"5","dept":"GENERAL-EYEWEAR","number":9611117797},
{"code":839050,"name":"BENJAMIN FELIX RAJKUMAR","email":"BENJAMIN@TITAN.CO.IN","level":"L7","dept":"HUMAN RESOURCES","number":9840100401},
{"code":839222,"name":"KARTHIK Y","email":"KARTHIKY@TITAN.CO.IN","level":"L7","dept":"MARKETING-TITAN","number":9731556556},
{"code":839577,"name":"NAVEEN PHULWANI","email":"NAVEENP@TITAN.CO.IN","level":"L7","dept":"RETAILING-TANISHQ","number":9916812684},
{"code":843288,"name":"TASLEEM ARIF S","email":"TASLEEM.A@TITAN.CO.IN","level":"L3","dept":"JEWELLERY-FINANCE","number":9611955009},
{"code":844275,"name":"MALVIKA KHADILKAR U","email":"MALVIKA@TITAN.CO.IN","level":"D2","dept":"DESIGNS","number":0},
{"code":844705,"name":"MANISH SRIDHAR","email":"MANISHS@TITAN.CO.IN","level":"L6","dept":"MARKETING EYEWEAR","number":9886402798},
{"code":845090,"name":"SRIKANTH SUDHARSANAN","email":"SRIKANTHS@TITAN.CO.IN","level":"L7","dept":"MERCHANDISING-TANISHQ","number":9243282259},
{"code":847763,"name":"SIVARAMAN R","email":"SIVARAMANR@TITAN.CO.IN","level":"L5","dept":"SYSTEMS","number":8904413396},
{"code":849210,"name":"PRAKASH V","email":"PRAKASH@TITAN.CO.IN","level":"L5","dept":"SYSTEMS","number":9566378743},
{"code":849651,"name":"ISHA SAPRA","email":"ISHAS@TITAN.CO.IN","level":"L7","dept":"RETAILING-TANISHQ","number":9916138550},
{"code":850487,"name":"NAVEEN N","email":"NAVEENN@TITAN.CO.IN","level":"L5","dept":"SYSTEMS","number":9986165829},
{"code":850573,"name":"BALASUBRAMANYA BHAT","email":"BALAB@TITAN.CO.IN","level":"L4","dept":"JEWELLERY-FINANCE","number":9964020882},
{"code":851119,"name":"LAKSHMI BALASUBRAMANIAN","email":"LAKSHMIB@TITAN.CO.IN","level":"L5","dept":"HUMAN RESOURCES","number":9945092654},
{"code":852375,"name":"SWAROOP KAMATH K","email":"SWAROOPK@TITAN.CO.IN","level":"L2","dept":"FINANCE","number":9916847281},
{"code":864423,"name":"ASHUTOSH PANDA","email":"ASHUTOSHP@TITAN.CO.IN","level":"L5","dept":"INTERNATIONAL OPERATIONS - TPD","number":9537003333},
{"code":865238,"name":"ADITHYA BHARGAV","email":"ADITHYAB@TITAN.CO.IN","level":"L4","dept":"FINANCE","number":0},
{"code":866666,"name":"SUDEEPTHI V J","email":"SUDEEPTHI@TITAN.CO.IN","level":"L6","dept":"INTERNATIONAL OPERATIONS - TPD","number":9980565368},
{"code":867126,"name":"SUDHAMANI K","email":"SUDHAMANI.K@TITAN.CO.IN","level":"L3","dept":"MERCHANDISING-HELIOS","number":9164003107},
{"code":873338,"name":"RAJARAM A R","email":"ARRAJARAM@TITAN.CO.IN","level":"3","dept":"LEGAL","number":9845024288},
{"code":874680,"name":"KUMAR V N","email":"KUMARVN@TITAN.CO.IN","level":"L5","dept":"ADMINISTRATION","number":9632566900},
{"code":876127,"name":"NARASINGHA PATRO","email":"NARASINGHA@TITAN.CO.IN","level":"L8","dept":"INTERNAL AUDIT","number":8050310551},
{"code":885042,"name":"KARANDEEP SINGH KAPANY","email":"KARANDEEPSK@TITAN.CO.IN","level":"L6","dept":"MARKETING-TANISHQ","number":9972621285},
{"code":885569,"name":"NALINI VEERAGHANTA","email":"NALINIV@TITAN.CO.IN","level":"L6","dept":"SALES-CERAMIC PRODUCTS","number":9739710519},
{"code":885655,"name":"MANEESH KRISHNAMURTHY","email":"MANEESHK@TITAN.CO.IN","level":"L6","dept":"SALES-CERAMIC PRODUCTS","number":9008027956},
{"code":889958,"name":"JOHN PAUL F","email":"JOHNP@TITAN.CO.IN","level":"L1","dept":"FINANCE","number":8050680710},
{"code":893314,"name":"NEHA JAISWAL","email":"NEHAJ@TITAN.CO.IN","level":"L5","dept":"MARKETING-GOLD PLUS","number":9972400244},
{"code":894301,"name":"HEMAND M","email":"HEMAND@TITAN.CO.IN","level":"D2","dept":"DESIGNS","number":9945586494},
{"code":897004,"name":"GNANAVEL P","email":"GNANAVELP@TITAN.CO.IN","level":"L4","dept":"RETAILING-TANISHQ","number":9790401426},
{"code":897359,"name":"ARUN KUMAR SHUKLA","email":"ASHUKLA@TITAN.CO.IN","level":"L5","dept":"SYSTEMS","number":9632001669},
{"code":905030,"name":"SARANYA L","email":"SARANYAL@TITAN.CO.IN","level":"L5","dept":"CENTRAL TECHNOLOGY SERVICES","number":9731973006},
{"code":908260,"name":"CHANDRA PRASAD B C","email":"CHANDRAPRASAD@TITAN.CO.IN","level":"L4","dept":"SYSTEMS","number":9843240516},
{"code":912842,"name":"VIPIN NAIR","email":"VIPINNAIR@TITAN.CO.IN","level":"L6","dept":"RETAILING WATCHES","number":9686512738},
{"code":912928,"name":"JERALD MONTHERO B","email":"JERALD@TITAN.CO.IN","level":"L4","dept":"MERCHANDISING-TANISHQ","number":9980546908},
{"code":915104,"name":"GOVERDHANA KUDLIGI","email":"GOVERDHANAK@TITAN.CO.IN","level":"L6","dept":"MD OFFICE","number":9845892759},
{"code":915986,"name":"KESHAVA B R","email":"KESHAVA@TITAN.CO.IN","level":"L7","dept":"ADMINISTRATION","number":9731600042},
{"code":919063,"name":"GEETHAKRISHNAN","email":"GEETHAKRISHNAN@TITAN.CO.IN","level":"L7","dept":"MERCHANDISING-TANISHQ","number":9900515970},
{"code":919848,"name":"SANJAY SANJAY","email":"SANJAYKUMAR@TITAN.CO.IN","level":"L5","dept":"MARKETING-TANISHQ","number":9901235495},
{"code":919934,"name":"KANWALPREET KAUR","email":"KANWALPREET@TITAN.CO.IN","level":"L9","dept":"MARKETING-TITAN","number":0},
{"code":933461,"name":"VINAY BABU A T","email":"VINAYBABU@TITAN.CO.IN","level":"L6","dept":"FINANCE","number":0},
{"code":936078,"name":"JAMALUDDIN K A","email":"JAMALUDDIN.K@TITAN.CO.IN","level":"L3","dept":"JEWELLERY-FINANCE","number":9740877774},
{"code":946238,"name":"SHIVALINGESH C K","email":"SHIVALINGESH@TITAN.CO.IN","level":"L7","dept":"ECB","number":9845630816},
{"code":957213,"name":"VINITA LAKWAL","email":"VINITAL@TITAN.CO.IN","level":"D2","dept":"DESIGNS","number":9980033851},
{"code":957396,"name":"RAJESHA MARIGOWDA","email":"RAJESHAM@TITAN.CO.IN","level":"L4","dept":"DESIGNS","number":9880644070},
{"code":960722,"name":"VENKATARAMI REDDY V","email":"VENKATAREDDYV@TITAN.CO.IN","level":"L5","dept":"SYSTEMS","number":7204346340},
{"code":961892,"name":"RAGHAVENDRA KULKARNI","email":"RAGHAVENDRAK@TITAN.CO.IN","level":"L4","dept":"DESIGNS","number":9986089144},
{"code":961978,"name":"LOKAPRIYA C","email":"LOKAPRIYA@TITAN.CO.IN","level":"L3","dept":"FINANCE-EYEWEAR","number":9986463148},
{"code":964595,"name":"DONA MANUEL","email":"DONAM@TITAN.CO.IN","level":"L5","dept":"SYSTEMS","number":9986547741},
{"code":970280,"name":"VINAY KUMAR JAIN","email":"VINAYK@TITAN.CO.IN","level":"L6","dept":"INTERNAL AUDIT","number":9916150509},
{"code":972781,"name":"POONAM MANDAVA","email":"POONAMMANDAVA@TITAN.CO.IN","level":"L5","dept":"HUMAN RESOURCES","number":7829817359},
{"code":976471,"name":"JAIKISHEN MEHTA","email":"JAIKISHEN@TITAN.CO.IN","level":"L7","dept":"MARKETING-TITAN","number":9902943700},
{"code":976729,"name":"PRAMILA M S","email":"PRAMILAMS@TITAN.CO.IN","level":"L3","dept":"FINANCE","number":0},
{"code":976815,"name":"RAKESH M","email":"MRAKESH@TITAN.CO.IN","level":"L4","dept":"FINANCE","number":0},
{"code":981427,"name":"SUBRAMANIAM S","email":"SUBRAMANIAMS@TITAN.CO.IN","level":"","dept":"FINANCE","number":9902945800},
{"code":982156,"name":"GOVINDARAJA PRABHU","email":"GOVINDARAJAP@TITAN.CO.IN","level":"L3","dept":"FINANCE","number":9632701419},
{"code":982328,"name":"UMESH HADAGALI","email":"UMESHH@TITAN.CO.IN","level":"L4","dept":"FINANCE","number":9741057587},
{"code":990514,"name":"MAHESH S","email":"MAHESHS@TITAN.CO.IN","level":"L2","dept":"LEGAL","number":9844336388},
{"code":993572,"name":"REEMA VAZIRANI","email":"REEMAV@TITAN.CO.IN","level":"L7","dept":"MARKETING-FASTRACK","number":9686950370},
{"code":998163,"name":"SARANYA S","email":"SARANYAS@TITAN.CO.IN","level":"L3","dept":"E-COMMERCE GENERAL","number":8754298894},
{"code":998335,"name":"SWARNALATHA KASTURI","email":"SWARNALATHA@TITAN.CO.IN","level":"L3","dept":"FINANCE","number":9008650918},
{"code":999935,"name":"SASI KIRAN BATTEPATI","email":"SASIKIRAN@TITAN.CO.IN","level":"L5","dept":"LARGE FORMAT STORES","number":9674088988},
{"code":1000517,"name":"BEATE STEINFELD","email":"BEATE@TITAN.CO.IN","level":"L9","dept":"DESIGNS-TANISHQ","number":9008167704},
{"code":1005022,"name":"VIJAY THOMPSON B","email":"VIJAYT@TITAN.CO.IN","level":"L5","dept":"LARGE FORMAT STORES","number":0},
{"code":1012490,"name":"SANGEETHA DEV","email":"SANGEETHAD@TITAN.CO.IN","level":"L5","dept":"RETAIL PROJECTS","number":9731338732},
{"code":1013391,"name":"NIDHI PRAKASH KAUL","email":"NPKAUL@TITAN.CO.IN","level":"D3","dept":"DESIGNS","number":9845812406},
{"code":1014464,"name":"AVINASH PAI T","email":"AVINASHP@TITAN.CO.IN","level":"L3","dept":"FINANCE","number":9741851888},
{"code":1015623,"name":"AVANI DESAI","email":"AVANI@TITAN.CO.IN","level":"L6","dept":"MARKETING-TITAN","number":9740075945},
{"code":1015709,"name":"ROSHAN A C","email":"ROSHANAC@TITAN.CO.IN","level":"L4","dept":"FINANCE","number":0},
{"code":1019668,"name":"RAMYA RAMACHANDRAN","email":"RAMYAR@TITAN.CO.IN","level":"L6","dept":"MARKETING-SONATA","number":9663888944},
{"code":1021921,"name":"LEKHA SHASTRY","email":"LEKHAS@TITAN.CO.IN","level":"L5","dept":"VISUAL MERCHANDISING-TANISHQ","number":9986431862},
{"code":1041639,"name":"SHANKARA R N","email":"SHANKARARN@TITAN.CO.IN","level":"L4","dept":"VISUAL MERCHANDISING-TANISHQ","number":9945611358},
{"code":1043527,"name":"DHARSINE T","email":"DHARSINET@TITAN.CO.IN","level":"L5","dept":"SYSTEMS","number":0},
{"code":1044697,"name":"NANDINI L N","email":"NANDINILN@TITAN.CO.IN","level":"L5","dept":"SYSTEMS","number":9620132954},
{"code":1045942,"name":"RAJASANKAR R","email":"RAJASANKAR@TITAN.CO.IN","level":"L5","dept":"SYSTEMS","number":8197394338},
{"code":1046402,"name":"SANGEETHA B N","email":"SANGEETHABN@TITANWORLD.COM","level":"L5","dept":"LARGE FORMAT STORES","number":9742815416},
{"code":1047303,"name":"YAMINI A","email":"YAMINIA@TITAN.CO.IN","level":"L5","dept":"SYSTEMS","number":7259828009},
{"code":1048559,"name":"MOLAY GHOSH","email":"MOLAYG@TITAN.CO.IN","level":"L5","dept":"MARKETING-TITAN","number":9663094378},
{"code":1050995,"name":"SWATI GEHANI","email":"SWATIGEHANI@TITAN.CO.IN","level":"D2","dept":"DESIGNS-TANISHQ","number":7676480329},
{"code":1058289,"name":"SIVA SUNDARA SARMA V","email":"VSSSARMA@TITAN.CO.IN","level":"L3","dept":"MERCHANDISING-TANISHQ","number":9618558100},
{"code":1064146,"name":"EVELYNE EDWINA D'SOUZA","email":"EVELYNE@TITAN.CO.IN","level":"D2","dept":"DESIGNS","number":9620824374},
{"code":1069264,"name":"SHIBANI K B","email":"SHIBANI@TITAN.CO.IN","level":"L5","dept":"MARKETING-FASTRACK","number":9886790332},
{"code":1072859,"name":"SUPRIYAA UTHAIAH","email":"SUPRIYAA@TITAN.CO.IN","level":"L5","dept":"MARKETING-FASTRACK","number":9900276913},
{"code":1074048,"name":"MADHAVI LATHA GARIMELLA","email":"MADHAVIL@TITAN.CO.IN","level":"L5","dept":"FINANCE","number":9010682053},
{"code":1074306,"name":"VIDYASHREE H G","email":"VIDYASHREE@TITAN.CO.IN","level":"L3","dept":"FINANCE","number":8277680964},
{"code":1077364,"name":"ANOOSHA","email":"ANOOSHA@TITAN.CO.IN","level":"L3","dept":"RETAILING-GOLD PLUS","number":9743640490},
{"code":1079510,"name":"SAURABH KUMAR","email":"SAURABHK@TITAN.CO.IN","level":"L5","dept":"DESIGNS-TANISHQ","number":8050655814},
{"code":1086365,"name":"SNEHA J","email":"SNEHAJ@TITAN.CO.IN","level":"L4","dept":"SYSTEMS","number":9845940500},
{"code":1086451,"name":"NAVEEN KUMAR N C","email":"KUMARNC@TITAN.CO.IN","level":"L5","dept":"SAFETY","number":9972356666},
{"code":1090420,"name":"CHANDRAKALA P V","email":"KALA@TITAN.CO.IN","level":"L3","dept":"DESIGNS-TANISHQ","number":9480357296},
{"code":1090775,"name":"RAGHAVENDRA V K","email":"RAGHAVENDRAVK@TITAN.CO.IN","level":"L3","dept":"FINANCE-TANISHQ","number":9964785009},
{"code":1090861,"name":"RASHMI M A","email":"RASHMIM@TITAN.CO.IN","level":"L3","dept":"MARKETING-TANISHQ","number":7829655524},
{"code":1092577,"name":"MOHAN M","email":"MOHAN@TITAN.CO.IN","level":"L4","dept":"DESIGNS","number":9945831473},
{"code":1092663,"name":"PAULINE PRESANNA KUMARI","email":"PAULINES@TITAN.CO.IN","level":"L3","dept":"FRAGRANCES-SALES","number":9916992453},
{"code":1092749,"name":"ANNIE CHRISTINA R","email":"ANNIE@TITAN.CO.IN","level":"L3","dept":"MARKETING-GOLD PLUS","number":9886349096},
{"code":1096611,"name":"RAJESHWARI K","email":"RAJESHWARI@TITAN.CO.IN","level":"L4","dept":"INTEGRATED RETAIL SERVICES","number":9972431966},
{"code":1103123,"name":"BANSI BELLIAPPA","email":"BANSIB@TITAN.CO.IN","level":"L5","dept":"LARGE FORMAT STORES","number":9845299344},
{"code":1104637,"name":"HEMANTH M C","email":"HEMANTHMC@TITAN.CO.IN","level":"L5","dept":"RETAIL PROJECTS","number":9582369966},
{"code":1104992,"name":"AMRIT PAL SINGH","email":"AMRITPS@TITAN.CO.IN","level":"L7","dept":"INTERNATIONAL OPERATIONS - TPD","number":9029005803},
{"code":1105366,"name":"VIDYASHANKAR SRINIVASAN","email":"VIDYASHANKARS@TITAN.CO.IN","level":"L5","dept":"MARKETING-FASTRACK","number":9535277118},
{"code":1105452,"name":"KARTHIKEYAN R","email":"KARTHIKEYAN.R@TITAN.CO.IN","level":"L4","dept":"MARKETING-TANISHQ","number":8885691105},
{"code":1110763,"name":"ANUBHAV AICH","email":"ANUBHAVA@TITAN.CO.IN","level":"D2","dept":"DESIGNS","number":9535041976},
{"code":1111051,"name":"SHASHANK GOWDA","email":"SHASHANKG@TITAN.CO.IN","level":"L6","dept":"VISUAL MERCHANDISING-TANISHQ","number":9880278112},
{"code":1111578,"name":"ISHITA KUMAR","email":"ISHITA@TITAN.CO.IN","level":"L5","dept":"DESIGNS-TANISHQ","number":9886474482},
{"code":1112479,"name":"NAVIN KUMAR","email":"NAVINKUMAR@TITAN.CO.IN","level":"L5","dept":"GOLD PLUS","number":9986119513},
{"code":1112737,"name":"MADAN KUMAR T S","email":"MADANTS@TITAN.CO.IN","level":"L3","dept":"RETAILING-EYEWEAR","number":9845111121},
{"code":1112823,"name":"KRISHNAJI RAO G","email":"KRISHNAJIRAO@TITAN.CO.IN","level":"L2","dept":"MARKETING EYEWEAR","number":9945435315},
{"code":1115881,"name":"VISHWANATH G HEGDE","email":"VISHWA@TITAN.CO.IN","level":"L9","dept":"FINANCE","number":9448364936},
{"code":1116954,"name":"ANANTHA R","email":"ANANTHAR@TITAN.CO.IN","level":"L4","dept":"SUPPLY CHAIN AND LOGISTICS","number":9591565120},
{"code":1117328,"name":"THIMMA REDDY S","email":"THIMMAR@TITAN.CO.IN","level":"L3","dept":"FINANCE","number":9036706098},
{"code":1119657,"name":"CHETAN SHARMA","email":"CHETANSHARMA@TITAN.CO.IN","level":"D2","dept":"DESIGNS","number":0},
{"code":1125955,"name":"ANITHA P","email":"ANITHAS@TITAN.CO.IN","level":"L3","dept":"RETAILING-EYEWEAR","number":9900964486},
{"code":1130825,"name":"KRATI DHOOT","email":"KRATI.D@TITAN.CO.IN","level":"L7","dept":"FINANCE","number":9741455522},
{"code":1131468,"name":"ABINAYA V","email":"ABINAYAV@TITAN.CO.IN","level":"L4","dept":"SYSTEMS","number":9047494466},
{"code":1138119,"name":"MANSOOR ALI KHAN","email":"MANSOOR@TITAN.CO.IN","level":"L6","dept":"MARKETING-TITAN","number":9880614658},
{"code":1139020,"name":"RASHMI R","email":"RASHMI@TITAN.CO.IN","level":"L3","dept":"MARKETING-TITAN","number":9980890700},
{"code":1139289,"name":"ROHITH K","email":"ROHITHK@TITAN.CO.IN","level":"L3","dept":"DESIGNS","number":9740052718},
{"code":1140555,"name":"VAIBHAV KUMAR","email":"VAIBHAVK@TITAN.CO.IN","level":"L6","dept":"LARGE FORMAT STORES","number":9008931100},
{"code":1140996,"name":"MADHU NAIDU N","email":"MADHUN@TITAN.CO.IN","level":"L2","dept":"FINANCE","number":9632391718},
{"code":1142357,"name":"PABITRA MONDAL","email":"PABITRA@TITAN.CO.IN","level":"L6","dept":"INTERNAL AUDIT","number":9916135375},
{"code":1145060,"name":"RYAN CHARLES PEREIRA","email":"RYANP@TITAN.CO.IN","level":"L4","dept":"MARKETING-FASTRACK","number":9886436186},
{"code":1146488,"name":"PRAKASH K","email":"KPRAKASH@TITAN.CO.IN","level":"L3","dept":"LARGE FORMAT STORES","number":9743124555},
{"code":1147733,"name":"RUCHIR FALODIYA","email":"RUCHIR.F@TITAN.CO.IN","level":"L4","dept":"MARKETING-TANISHQ","number":0},
{"code":1154674,"name":"RAJASHEKAR H","email":"RAJSHEKAR@TITAN.CO.IN","level":"L3","dept":"HUMAN RESOURCES","number":9972866525},
{"code":1154846,"name":"SHEELA MANORAJ","email":"SHEELA@TITAN.CO.IN","level":"L2","dept":"SYSTEMS","number":0},
{"code":1158192,"name":"VEENA K","email":"VEENAK@TITAN.CO.IN","level":"L4","dept":"HUMAN RESOURCES","number":7259960733},
{"code":1159351,"name":"SHALVI AGGARWAL","email":"SHALVIA@TITAN.CO.IN","level":"L4","dept":"RETAILING WATCHES","number":0},
{"code":1159437,"name":"ANUPAMA THAKKAR","email":"ANUPAMAT@TITAN.CO.IN","level":"L4","dept":"RETAILING WATCHES","number":0},
{"code":1160004,"name":"NABEELA KHALED","email":"NABEELAK@TITAN.CO.IN","level":"L4","dept":"RETAILING WATCHES","number":8939620366},
{"code":1160445,"name":"GEORGE MEKAT","email":"GEORGEMEKAT@TITAN.CO.IN","level":"L7","dept":"MARKETING-GOLD PLUS","number":0},
{"code":1161959,"name":"MANIVANNAN P","email":"MANIVANNANP@TITAN.CO.IN","level":"L9","dept":"FINANCE","number":9900223390},
{"code":1163148,"name":"BINIT KUMAR PANDEY","email":"BINITP@TITAN.CO.IN","level":"L5","dept":"MARKETING-TITAN","number":0},
{"code":1164135,"name":"ANUPAM SAHA","email":"ANUPAMS@TITAN.CO.IN","level":"L6","dept":"MERCHANDISING - WAD","number":9900120438},
{"code":1164490,"name":"ARKAJYOTI ROY CHOWDHURY","email":"ARKA@TITAN.CO.IN","level":"L5","dept":"FINANCE","number":9769684341},
{"code":1164920,"name":"NANDINI KAPUR","email":"NANDINIK@TITAN.CO.IN","level":"L6","dept":"LARGE FORMAT STORES","number":9986621310},
{"code":1165036,"name":"PALLAVI SHETTY","email":"PALLAVIS@TITAN.CO.IN","level":"L6","dept":"MARKETING-TITAN","number":9620350731},
{"code":1165391,"name":"SAMPURNA RAKSHIT","email":"SAMPURNA@TITAN.CO.IN","level":"L5","dept":"MARKETING-ACCESSORIES","number":0},
{"code":1170519,"name":"RAJESH BABU P B","email":"RAJESHB@TITAN.CO.IN","level":"L5","dept":"COMMERCIAL","number":8792143474},
{"code":1170874,"name":"RAJAN AMBA","email":"RAMBA@TITAN.CO.IN","level":"4","dept":"MARKETING-TITAN","number":0},
{"code":1172321,"name":"SAMBIT PATTNAIK","email":"SAMBITP@TITAN.CO.IN","level":"L5","dept":"SYSTEMS","number":9611227449},
{"code":1173308,"name":"ANKITA KAPOOR","email":"ANKITAK@TITAN.CO.IN","level":"L4","dept":"MARKETING-ACCESSORIES","number":8884400924},
{"code":1174478,"name":"REVATHY RANGAN","email":"REVATHYR@TITAN.CO.IN","level":"T6","dept":"MARKETING-SONATA","number":0},
{"code":1175723,"name":"ANANTHANARAYANAN HARIHARAN","email":"ANANTHAN@TITAN.CO.IN","level":"4","dept":"MERCHANDISING-TANISHQ","number":9901688445},
{"code":1179854,"name":"ARJUN H G","email":"ARJUNHG@TITAN.CO.IN","level":"L3","dept":"MERCHANDISING-GOLD PLUS","number":9845538038},
{"code":1179940,"name":"ROHINI SOOD","email":"ROHINIS@TITAN.CO.IN","level":"L3","dept":"MERCHANDISING-GOLD PLUS","number":9986732201},
{"code":1186795,"name":"ANJU S","email":"ANJUS@TITAN.CO.IN","level":"L3","dept":"INTERNATIONAL OPERATIONS - TPD","number":9980466884},
{"code":1188328,"name":"KESAVA KUMAR M","email":"KESAVAKM@TITAN.CO.IN","level":"L3","dept":"DESIGNS-TANISHQ","number":9629407852},
{"code":1189928,"name":"VIGNESH G","email":"VIGNESHG@TITAN.CO.IN","level":"L4","dept":"SYSTEMS","number":7795190149},
{"code":1191052,"name":"MANJUNATHA K M","email":"MANJUNATHAKM@TITAN.CO.IN","level":"L4","dept":"SYSTEMS","number":9986418443},
{"code":1191138,"name":"ARUN KUMAR R","email":"ARUNKUMARR@TITAN.CO.IN","level":"L4","dept":"LARGE FORMAT STORES","number":9940362716},
{"code":1192394,"name":"RUTHVIK S","email":"RUTHVIK@TITAN.CO.IN","level":"L3","dept":"CENTRAL TECHNOLOGY SERVICES","number":9620522823},
{"code":1192910,"name":"MUHAMMED ANAS","email":"ANAS@TITAN.CO.IN","level":"L3","dept":"DESIGNS","number":8050458616},
{"code":1193639,"name":"RITURAJ SINGH","email":"RITURAJS@TITAN.CO.IN","level":"L4","dept":"SYSTEMS","number":9611335830},
{"code":1193725,"name":"SRUTHI MOHEN G","email":"SRUTHIG@TITAN.CO.IN","level":"D1","dept":"DESIGNS-TANISHQ","number":9902179355},
{"code":1194282,"name":"BASAVARAJU N M","email":"BASAVARAJUNM@TITAN.CO.IN","level":"L4","dept":"MERCHANDISING - WAD","number":9844162599},
{"code":1195355,"name":"MITHESH KESHAVA KULAL","email":"MITHESH@TITAN.CO.IN","level":"L4","dept":"MERCHANDISING - WAD","number":9611809077},
{"code":1195882,"name":"DHRUV BHATT","email":"DHRUVB@TITAN.CO.IN","level":"L4","dept":"MERCHANDISING - WAD","number":9611988427},
{"code":1205441,"name":"VIJAYA KUMAR S","email":"VIJAYSP@TITAN.CO.IN","level":"L6","dept":"SYSTEMS","number":9986713213},
{"code":1209572,"name":"PRASHANTH S","email":"PRASHANTHS@TITAN.CO.IN","level":"L5","dept":"COMMERCIAL","number":9448126622},
{"code":1209916,"name":"KARTHIK H","email":"KARTHIKH@TITAN.CO.IN","level":"L3","dept":"MARKETING-TITAN","number":9738833434},
{"code":1210752,"name":"UMA S","email":"UMA@TITAN.CO.IN","level":"L5","dept":"FINANCE","number":9663790087},
{"code":1211481,"name":"MALAVIKA KALAUNY","email":"MALAVIKAK@TITAN.CO.IN","level":"L7","dept":"FRAGRANCES-MARKETING","number":7259344484},
{"code":1220826,"name":"VAIRAVEL P","email":"VAIRAVELP@TITAN.CO.IN","level":"L4","dept":"CORPORATE SUSTAINABILITY","number":9443417853},
{"code":1224086,"name":"RAKSHITHA DEVIAH","email":"RAKSHITHA@TITAN.CO.IN","level":"L4","dept":"MARKETING-FASTRACK","number":9886260294},
{"code":1226845,"name":"SHWETA SHARMA","email":"SHWETA@TITAN.CO.IN","level":"D1","dept":"DESIGNS","number":9986578165},
{"code":1226931,"name":"MADHUSUDAN V","email":"MADHUSUDANV@TITAN.CO.IN","level":"L3","dept":"CUSTOMER LOYALTY AND ANALYTICS","number":0},
{"code":1231715,"name":"RAJNARAYAN R","email":"RAJNARAYAN@TITAN.CO.IN","level":"AVP","dept":"HUMAN RESOURCES","number":9611199113},
{"code":1232186,"name":"MOMITA DAS","email":"MOMITA@TITAN.CO.IN","level":"L5","dept":"CORPORATE GENERAL","number":9980557431},
{"code":1235319,"name":"ANTARJYAMI MAHARANA","email":"ANTARJYAMI@TITAN.CO.IN","level":"L2","dept":"JEWELLERY-FINANCE","number":8971197794},
{"code":1235846,"name":"ALOKEDEEP SINGH","email":"ALOKEDEEP@TITAN.CO.IN","level":"L9","dept":"E-COMMERCE GENERAL","number":9742030825},
{"code":1237734,"name":"SHERRY GEORGE","email":"SHERRYG@TITAN.CO.IN","level":"L6","dept":"CUSTOMER LOYALTY AND ANALYTICS","number":9663488188},
{"code":1238635,"name":"DEEPIKA SABHARWAL TEWARI","email":"DEEPIKAST@TITAN.CO.IN","level":"4","dept":"MARKETING-TANISHQ","number":9886202726},
{"code":1243247,"name":"SARFRAZ MOHAMMED","email":"SARFRAZ@TITAN.CO.IN","level":"L5","dept":"LARGE FORMAT STORES","number":8867070021},
{"code":1250188,"name":"PRAMOD H","email":"PRAMODH@TITAN.CO.IN","level":"L2","dept":"FINANCE","number":9972641511},
{"code":1257624,"name":"RAKESH B R","email":"RAKESHBR@TITAN.CO.IN","level":"L3","dept":"CUSTOMER LOYALTY AND ANALYTICS","number":9886952766},
{"code":1263492,"name":"RAJALAKSHMI P","email":"RAJALAKSHMI@TITAN.CO.IN","level":"L4","dept":"HUMAN RESOURCES","number":9886058322},
{"code":1264651,"name":"VIPIN CHANDRA LALIT","email":"VIPINL@TITAN.CO.IN","level":"L6","dept":"ECOMMERCE - GENERAL","number":9886445617},
{"code":1268954,"name":"BALASUBRAMANIAN T","email":"BALAT@TITAN.CO.IN","level":"L4","dept":"RETAIL PROJECTS","number":8144203239},
{"code":1272579,"name":"NAVEEN KUMAR D S","email":"NAVEENDS@TITAN.CO.IN","level":"L3","dept":"JEWELLERY-FINANCE","number":9902148446},
{"code":1273738,"name":"DIVYE SOOD","email":"DIVYES@TITAN.CO.IN","level":"L4","dept":"MARKETING-HELIOS","number":9930976470},
{"code":1276269,"name":"ANUDEEP KORLEPARA","email":"ANUDEEPK@TITAN.CO.IN","level":"L4","dept":"RETAILING-HELIOS","number":9030517301},
{"code":1283554,"name":"LOKESHA M","email":"LOKESHA.M@TITAN.CO.IN","level":"L1","dept":"FINANCE","number":9008053822},
{"code":1283640,"name":"INDIRA PRIYADARSINI V","email":"INDIRAP@TITAN.CO.IN","level":"L5","dept":"HUMAN RESOURCES","number":8861009922},
{"code":1286601,"name":"PIYUSH PANDEY","email":"PIYUSHP@TITAN.CO.IN","level":"L5","dept":"FRAGRANCES-SALES","number":9620410299},
{"code":1286784,"name":"HIMANSHU SHAH","email":"HIMANSHUS@TITAN.CO.IN","level":"L5","dept":"HUMAN RESOURCES","number":7677773666},
{"code":1287330,"name":"SIVA KUMAR PEDHAPATI","email":"SIVAKP@TITAN.CO.IN","level":"L5","dept":"RETAILING-EYEWEAR","number":9642945994},
{"code":1287502,"name":"NOOPUR BORWANKAR","email":"NOOPUR@TITAN.CO.IN","level":"L5","dept":"HUMAN RESOURCES","number":8974052784},
{"code":1287771,"name":"PRATIK BENGANI","email":"PRATIK@TITAN.CO.IN","level":"L5","dept":"MARKETING EYEWEAR","number":9538954350},
{"code":1287943,"name":"DEEPAK KUMAR SAHU","email":"DEEPAKKS@TITAN.CO.IN","level":"L5","dept":"SUPPLY CHAIN AND LOGISTICS","number":9437175976},
{"code":1288145,"name":"PUNEET JAIN","email":"PUNEETJ@TITAN.CO.IN","level":"L5","dept":"SYSTEMS","number":8879486424},
{"code":1288317,"name":"PRAGYA MADAR","email":"PRAGYA@TITAN.CO.IN","level":"L5","dept":"RETAILING-EYEWEAR","number":7275398678},
{"code":1289218,"name":"AVINASH RAMACHANDRAN","email":"AVINASHRA@TITAN.CO.IN","level":"L5","dept":"RETAILING WATCHES","number":0},
{"code":1289659,"name":"SANDEEPAN BHATTACHARYA","email":"SANDEEPANB@TITAN.CO.IN","level":"L5","dept":"RETAILING-EYEWEAR","number":9968434670},
{"code":1290581,"name":"HARSHA C","email":"HARSHAC@TITAN.CO.IN","level":"L4","dept":"SYSTEMS","number":9845404395},
{"code":1292813,"name":"ARUSHI SRIVASTAVA","email":"ARUSHIS@TITAN.CO.IN","level":"L2","dept":"MERCHANDISING-TANISHQ","number":8095131614},
{"code":1292996,"name":"DINU D","email":"DINU@TITAN.CO.IN","level":"L2","dept":"DESIGNS-TANISHQ","number":9747240865},
{"code":1294970,"name":"JIM GEORGE","email":"JIMGEORGE@TITAN.CO.IN","level":"L6","dept":"HUMAN RESOURCES","number":7208003466},
{"code":1295172,"name":"ARJUN MOHAN","email":"ARJUNM@TITAN.CO.IN","level":"T6","dept":"TRADE WATCHES","number":7208001701},
{"code":1295957,"name":"VIRENDRA PARIHAR","email":"VIRENDRAP@TITAN.CO.IN","level":"L4","dept":"MERCHANDISING-TANISHQ","number":9252197078},
{"code":1296686,"name":"MALVIKA SAINATH","email":"MALVIKAS@TITAN.CO.IN","level":"D1","dept":"DESIGNS","number":8452910655},
{"code":1297232,"name":"AJAY MAURYA","email":"AJAYM@TITAN.CO.IN","level":"T6","dept":"MARKETING-TITAN","number":9818329077},
{"code":1302641,"name":"NAGABUSHAN RAO M","email":"NAGABUSHAN@TITAN.CO.IN","level":"L3","dept":"CENTRAL TECHNOLOGY SERVICES","number":9611784233},
{"code":1307060,"name":"ANDRIA M","email":"ANDRIAM@TITAN.CO.IN","level":"L4","dept":"SYSTEMS","number":0},
{"code":1308574,"name":"KARTHIKEYAN S","email":"KARTHIKEYA@TITAN.CO.IN","level":"L4","dept":"CENTRAL TECHNOLOGY SERVICES","number":8197548783},
{"code":1309034,"name":"NARAYAN A S","email":"ASNARAYAN@TITAN.CO.IN","level":"L4","dept":"CENTRAL TECHNOLOGY SERVICES","number":8105671358},
{"code":1309206,"name":"PARIKSHIT SHETTY","email":"PARIKSHITHSHETTY@TITAN.CO.IN","level":"L4","dept":"SYSTEMS","number":8277296530},
{"code":1309389,"name":"POORNIMA S P","email":"POORNIMASP@TITAN.CO.IN","level":"L4","dept":"SYSTEMS","number":7353539060},
{"code":1309647,"name":"PRASANTH REDDY BURRAMUKKU","email":"PRASANTHREDDY@TITAN.CO.IN","level":"L4","dept":"CENTRAL TECHNOLOGY SERVICES","number":9600642444},
{"code":1312629,"name":"AFRAH BANU","email":"AFRAHBANU@TITAN.CO.IN","level":"L2","dept":"MERCHANDISING-GOLD PLUS","number":9844990512},
{"code":1312715,"name":"KEITH JUDE D'SOUZA","email":"KEITH@TITAN.CO.IN","level":"D1","dept":"DESIGNS","number":7927495561},
{"code":1314517,"name":"MARY FRANCINA F","email":"MARYFRANCINA@TITAN.CO.IN","level":"L2","dept":"FINANCE","number":8147557364},
{"code":1315773,"name":"RAHUL SRINIVAS","email":"RAHULS@TITAN.CO.IN","level":"L7","dept":"HUMAN RESOURCES","number":7926761611},
{"code":1318820,"name":"SHREEDHAR HEGDE","email":"SHREEHEGDE@TITAN.CO.IN","level":"L8","dept":"LEGAL","number":9880297722},
{"code":1318906,"name":"SHRUTI SHRIKANT NILEGAONKAR","email":"SHRUTINILEGAOKAR@TITAN.CO.IN","level":"D1","dept":"DESIGNS","number":9901827911},
{"code":1319022,"name":"APARAJITA SHANKAR","email":"APARAJITA@TITAN.CO.IN","level":"L7","dept":"HUMAN RESOURCES","number":7738827888},
{"code":1323260,"name":"SANDHYA NAIR","email":"SANDHYANAIR@TITAN.CO.IN","level":"L4","dept":"SYSTEMS","number":9986118987},
{"code":1325148,"name":"FLAURA SHUKLA","email":"FLAURA@TITAN.CO.IN","level":"D1","dept":"DESIGNS","number":9958765283},
{"code":1326834,"name":"PURUSHARTH","email":"PURUSHARTH@TITAN.CO.IN","level":"L4","dept":"VISUAL MERCHANDISING-TANISHQ","number":9739805994},
{"code":1333420,"name":"SONI MISHRA","email":"SONIMISHRA@TITAN.CO.IN","level":"GM","dept":"HUMAN RESOURCES","number":9820135906},
{"code":1334676,"name":"DHANYA K","email":"DHANYAK@TITAN.CO.IN","level":"L6","dept":"HUMAN RESOURCES","number":9790976866},
{"code":1336478,"name":"JITENDRA SEKHANI","email":"JITENDRAS@TITAN.CO.IN","level":"L5","dept":"INTERNAL AUDIT","number":9163581189},
{"code":1349169,"name":"NAYAN NEGI","email":"NAYANNEGI@TITAN.CO.IN","level":"L4","dept":"MARKETING-TITAN","number":8951299209},
{"code":1352936,"name":"DEEPIKA DHIMAN","email":"DEEPIKADHIMAN@TITAN.CO.IN","level":"L4","dept":"VISUAL MERCHANDISING-TANISHQ","number":9811959639},
{"code":1359157,"name":"SHAMAYITA DEBNATH","email":"SHAMAYITA@TITAN.CO.IN","level":"L4","dept":"VISUAL MERCHANDISING-TANISHQ","number":9845439863},
{"code":1361851,"name":"DEEPA M C","email":"DEEPAMC@TITAN.CO.IN","level":"L3","dept":"CORPORATE SUSTAINABILITY","number":9886657754},
{"code":1363126,"name":"SHIVAKUMAR K","email":"SHIVAKUMAR@TITAN.CO.IN","level":"L3","dept":"SYSTEMS","number":9819044265},
{"code":1364027,"name":"DEVENDRA B K","email":"DEVENDRA@TITAN.CO.IN","level":"L5","dept":"LEGAL","number":9482435802},
{"code":1366883,"name":"RHONAC K S","email":"RHONACKS@TITAN.CO.IN","level":"L4","dept":"LEGAL","number":9886127136},
{"code":1367257,"name":"HEMANTH KUMAR M","email":"HEMANTHKUMAR@TITAN.CO.IN","level":"L5","dept":"FINANCE","number":9902023027},
{"code":1368072,"name":"PRASHANTH U K","email":"PRASHANTHUK@TITAN.CO.IN","level":"L5","dept":"CUSTOMER LOYALTY AND ANALYTICS","number":9060138990},
{"code":1371140,"name":"MONICA PRASAD","email":"MONICAPRASAD@TITAN.CO.IN","level":"L7","dept":"HUMAN RESOURCES","number":9980540706},
{"code":1373996,"name":"ANAIKA JAGGAROW","email":"ANAIKA@TITAN.CO.IN","level":"L5","dept":"MARKETING-FASTRACK","number":9741633447},
{"code":1375357,"name":"BHAYYAPU REDDY M","email":"BHAYYAPU@TITAN.CO.IN","level":"L3","dept":"FINANCE","number":7406201815},
{"code":1376172,"name":"SANTOSH KUMAR VUPPALA","email":"SANTOSHKV@TITAN.CO.IN","level":"L7","dept":"CUSTOMER LOYALTY AND ANALYTICS","number":9538894420},
{"code":1378587,"name":"SARADWATI MITRA DEY","email":"SARADWATI@TITAN.CO.IN","level":"L5","dept":"MERCHANDISING-TANISHQ","number":9886860028},
{"code":1381397,"name":"RAMESH BHAT K","email":"RAMESHBHAT@TITAN.CO.IN","level":"L7","dept":"LEGAL","number":9632961291},
{"code":1381483,"name":"SAGAR P S","email":"SAGARPS@TITANWORLD.COM","level":"L3","dept":"DESIGNS","number":8867650002},
{"code":1382115,"name":"ANAGHA A RAO","email":"ANAGHA@TITAN.CO.IN","level":"L4","dept":"SYSTEMS","number":7760119205},
{"code":1382556,"name":"GURKIRANDEEP SINGH","email":"GURKIRANDEEP@TITAN.CO.IN","level":"GM","dept":"HUMAN RESOURCES","number":9845123964},
{"code":1382997,"name":"SIVA ANUMANI GIRISH KUMAR","email":"GIRISHKUMAR@TITAN.CO.IN","level":"L5","dept":"TRADE-WATCHES","number":8978962553},
{"code":1383102,"name":"JASWANT THADI","email":"JASWANT@TITAN.CO.IN","level":"L5","dept":"SALES-TANISHQ","number":8912530217},
{"code":1383285,"name":"TANYA BENIWAL","email":"TANYA@TITAN.CO.IN","level":"L5","dept":"HUMAN RESOURCES","number":9414089333},
{"code":1383371,"name":"UDAY SHARMA","email":"UDAYSHARMA@TITAN.CO.IN","level":"L5","dept":"E-COMMERCE GENERAL","number":9212632124},
{"code":1383457,"name":"SHASHI KUMAR","email":"SHASHIKUMAR@TITAN.CO.IN","level":"L5","dept":"RETAILING - GOLD PLUS","number":8294490015},
{"code":1383543,"name":"BIPIN PINJANI","email":"BIPIN@TITAN.CO.IN","level":"L5","dept":"HUMAN RESOURCES","number":9922789793},
{"code":1383629,"name":"AKANKSHA BALI","email":"AKANKSHA@TITAN.CO.IN","level":"L5","dept":"SALES-TANISHQ","number":9660894884},
{"code":1383715,"name":"AMY THOMAS","email":"AMYTHOMAS@TITAN.CO.IN","level":"L5","dept":"LARGE FORMAT STORES","number":9496455155},
{"code":1383801,"name":"PRANOTI WAINGANKAR","email":"PRANOTI@TITAN.CO.IN","level":"L5","dept":"SALES-TANISHQ","number":9323906881},
{"code":1383984,"name":"UTKAL DESAI","email":"UTKAL@TITAN.CO.IN","level":"L5","dept":"RETAILING-EYEWEAR","number":9769416720},
{"code":1384186,"name":"SUDHANSHU DWIVEDI","email":"SUDHANSHU@TITAN.CO.IN","level":"L5","dept":"SALES-TANISHQ","number":9462692167},
{"code":1384272,"name":"HAPPY GARG","email":"HAPPYGARG@TITAN.CO.IN","level":"L5","dept":"RETAIL TRAINING","number":9927774560},
{"code":1384444,"name":"AKASH DOHAREY","email":"AKASHDOHAREY@TITAN.CO.IN","level":"L5","dept":"HUMAN RESOURCES","number":9632119213},
{"code":1384530,"name":"AMIT RANA","email":"AMITRANA@TITAN.CO.IN","level":"L5","dept":"JEWELLERY GENERAL","number":9917888536},
{"code":1384616,"name":"AKASH DUTTA","email":"AKASHDUTTA@TITAN.CO.IN","level":"L5","dept":"JEWELLERY GENERAL","number":9861588056},
{"code":1384885,"name":"KARAN RAJAN UMRALKAR","email":"KARAN@TITAN.CO.IN","level":"L5","dept":"TRADE-WATCHES","number":9769029777},
{"code":1384971,"name":"RATAN TAPARIA","email":"RATAN@TITAN.CO.IN","level":"L5","dept":"RETAILING-HELIOS","number":9831219644},
{"code":1385087,"name":"MITHINGA BASUMATARY","email":"MITHINGA@TITAN.CO.IN","level":"L5","dept":"RETAILING-EYEWEAR","number":8697078266},
{"code":1388747,"name":"NIKET VARMA","email":"NIKET@TITAN.CO.IN","level":"L5","dept":"RETAILING-TANISHQ","number":8105708298},
{"code":1389648,"name":"NAIRUTI SHARMA","email":"SHARMANAIRUTI@TITAN.CO.IN","level":"L4","dept":"VISUAL MERCHANDISING-TANISHQ","number":9742672259},
{"code":1393187,"name":"SMRITI PRATISHRUTI","email":"SMRITI@TITAN.CO.IN","level":"L5","dept":"HUMAN RESOURCES","number":9556287752},
{"code":1394088,"name":"MOHINEESH YALAMANCHILI","email":"MOHINEESHY@TITAN.CO.IN","level":"T6","dept":"MARKETING EYEWEAR","number":9867733722},
{"code":1394174,"name":"CHIRAG SHARAD HEDA","email":"CHIRAGH@TITAN.CO.IN","level":"T6","dept":"MARKETING-EYEWEAR","number":9833887215},
{"code":1395505,"name":"HARSHAD SARDESHMUKH A","email":"HARSHAD@TITAN.CO.IN","level":"T6","dept":"MARKETING-SONATA","number":9769678015},
{"code":1395860,"name":"SANKET BALGI","email":"SANKETP@TITAN.CO.IN","level":"L4","dept":"TRADE WATCHES","number":9663893313},
{"code":1396148,"name":"SAMIK GHOSH","email":"SAMIKGHOSH@TITAN.CO.IN","level":"L5","dept":"FINANCE","number":9739778805},
{"code":1396234,"name":"GOPA GANESH K","email":"GOPAGANESH@TITAN.CO.IN","level":"L5","dept":"INTERNAL AUDIT","number":9686803667},
{"code":1396589,"name":"BISWADEEP SARKAR","email":"BISWADEEP@TITAN.CO.IN","level":"L4","dept":"TRADE WATCHES","number":9088173716},
{"code":1398036,"name":"RANJANI D","email":"RANJANID@TITAN.CO.IN","level":"L4","dept":"SYSTEMS","number":9611490807},
{"code":1399636,"name":"KEERTHI KUMAR M","email":"KEERTHIKUMAR@TITAN.CO.IN","level":"L2","dept":"FINANCE","number":9538481598},
{"code":1401116,"name":"RAMESH POTULA","email":"RAMESHPOTULA@TITAN.CO.IN","level":"L5","dept":"SYSTEMS","number":9738341847},
{"code":1401471,"name":"MOHAN HS","email":"MOHANHS@TITAN.CO.IN","level":"L2","dept":"FINANCE","number":9035997109},
{"code":1401729,"name":"KAMLESH SINGH","email":"KAMLESHS@TITAN.CO.IN","level":"L4","dept":"ECOMMERCE - GENERAL","number":9035191876},
{"code":1401815,"name":"GAYATHRI RANGANATHAN","email":"GAYATHRIR@TITAN.CO.IN","level":"L4","dept":"LARGE FORMAT STORES","number":9995228460},
{"code":1407576,"name":"RAJSHREE CHANDRA","email":"RAJSHREECHANDRA@TITAN.CO.IN","level":"L5","dept":"MERCHANDISING-HELIOS","number":9686115560},
{"code":1407920,"name":"SHYAM PRAKASH N","email":"SHYAMPRAKASHN@TITAN.CO.IN","level":"L4","dept":"SYSTEMS","number":9566659637},
{"code":1412532,"name":"SUJITH SUDHAKARAN","email":"SUJITHS@TITAN.CO.IN","level":"L8","dept":"MARKETING-TANISHQ","number":9980758855},
{"code":1415149,"name":"ANUSHREE AGARWAL","email":"ANUSHREE@TITAN.CO.IN","level":"L6","dept":"MARKETING-HELIOS","number":7259253324},
{"code":1415407,"name":"ROHIT RAJEN","email":"ROHITRAJEN@TITAN.CO.IN","level":"L6","dept":"MARKETING-FASTRACK","number":9743999785},
{"code":1415848,"name":"LAKSHMI TOSHNIWAL","email":"TLAKSHMI@TITAN.CO.IN","level":"L8","dept":"HUMAN RESOURCES","number":9880017294},
{"code":1416050,"name":"SHUBHRA SAXENA","email":"SHUBHRASAXENA@TITAN.CO.IN","level":"L3","dept":"CUSTOMER LOYALTY AND ANALYTICS","number":9008882296},
{"code":1417822,"name":"NEHA SINGH","email":"NEHAS@TITAN.CO.IN","level":"D1","dept":"DESIGNS-TANISHQ","number":9662542342},
{"code":1418024,"name":"ILA MISHRA","email":"ILA@TITAN.CO.IN","level":"L4","dept":"MARKETING-TITAN","number":9415019465},
{"code":1419893,"name":"RICHA SARMA","email":"RICHAS@TITAN.CO.IN","level":"L5","dept":"MARKETING EYEWEAR","number":9986189242},
{"code":1420019,"name":"KAVITHA SELVAN P","email":"KAVITHASELVAN@TITAN.CO.IN","level":"L4","dept":"SYSTEMS","number":9942699024},
{"code":1420288,"name":"INDUJ DAMODAR","email":"DAMODAR.I@TITAN.CO.IN","level":"L5","dept":"MARKETING EYEWEAR","number":9740546400},
{"code":1421006,"name":"RAKESH NARAYAN","email":"RAKESHNARAYAN@TITAN.CO.IN","level":"L8","dept":"BUSINESS DEVELOPMENT-IRSG","number":9819798850},
{"code":1421974,"name":"KIRAN S R","email":"KIRANSR@TITAN.CO.IN","level":"L8","dept":"ADMINISTRATION","number":9036858959},
{"code":1424408,"name":"RAMESH BABU G S","email":"RAMESHGS@TITAN.CO.IN","level":"L3","dept":"MERCHANDISING-TANISHQ","number":9611512408},
{"code":1426393,"name":"GRISHMA MUDDAPPA","email":"GRISHMA@TITAN.CO.IN","level":"L4","dept":"MARKETING-FASTRACK","number":9739835037},
{"code":1426737,"name":"RAJ KUMAR DEVANURI","email":"RAJKUMARDEV@TITAN.CO.IN","level":"L6","dept":"RETAILING-HELIOS","number":9164278855},
{"code":1427810,"name":"MITHUN PRAKASH","email":"MITHUNPRAKASH@TITAN.CO.IN","level":"L5","dept":"MARKETING-TITAN","number":7259649552},
{"code":1428195,"name":"JANANI JAYARAMAN","email":"JANANIJAYARAMAN@TITAN.CO.IN","level":"L4","dept":"SYSTEMS","number":9886789506},
{"code":1428539,"name":"RAHUL S","email":"RAHULDAVID@TITAN.CO.IN","level":"L4","dept":"INTEGRATED RETAIL SERVICES","number":9738048856},
{"code":1429612,"name":"IMMACULATE DHIVYA","email":"DHIVYA.IMMACULATE@TITAN.CO.IN","level":"L2","dept":"FINANCE","number":8220485634},
{"code":1429881,"name":"PURNOOR SINGH SODHI","email":"PURNOOR@TITAN.CO.IN","level":"T6","dept":"MERCHANDISING-TANISHQ","number":8861219900},
{"code":1431435,"name":"NITHIN BHAT S","email":"NITHINBHAT@TITAN.CO.IN","level":"L2","dept":"RETAILING-EYEWEAR","number":8277196588},
{"code":1431876,"name":"SARANYA V","email":"SARANYAV@TITAN.CO.IN","level":"L2","dept":"FINANCE","number":9842116448},
{"code":1434310,"name":"VIKASH KUMAR","email":"VIKASH@TITAN.CO.IN","level":"L4","dept":"SYSTEMS","number":9035807815},
{"code":1435394,"name":"PADMAJA SAKSENA","email":"PADMAJAD@TITAN.CO.IN","level":"L8","dept":"HUMAN RESOURCES","number":9845848676},
{"code":1436553,"name":"PRATHVIRAJ KEEKAN P","email":"PRITHVIRAJ@TITAN.CO.IN","level":"L4","dept":"SUPPLY CHAIN MANAGEMENT","number":9742508005},
{"code":1437454,"name":"PRAVEEN KUMAR H HADIMANI","email":"PRAVEENK@TITAN.CO.IN","level":"L5","dept":"CUSTOMER LOYALTY AND ANALYTICS","number":9962264429},
{"code":1437895,"name":"KARTHIK SUMANTH DUMPALA","email":"KARTHIKSD@TITAN.CO.IN","level":"L5","dept":"SYSTEMS","number":9620172887},
{"code":1441864,"name":"SATHIYASEELAN J","email":"SATHYASEELAN@TITAN.CO.IN","level":"L3","dept":"DESIGNS-TANISHQ","number":9659999566},
{"code":1442152,"name":"SHILPA CHAKRAWARTI","email":"SHILPACHAKRAWARTI@TITAN.CO.IN","level":"L4","dept":"RETAILING-HELIOS","number":7626272713},
{"code":1442593,"name":"SRINIVASA MURTHY K","email":"SRINIVASAMURTHY@TITAN.CO.IN","level":"L3","dept":"LARGE FORMAT STORES","number":9740262238},
{"code":1442851,"name":"GOKUL KINGSLEY JERALD","email":"GOKUL@TITAN.CO.IN","level":"L3","dept":"LARGE FORMAT STORES","number":9739075110},
{"code":1445382,"name":"ARUSH AGARWAL","email":"ARUSH@TITAN.CO.IN","level":"D1","dept":"DESIGNS","number":9818206914},
{"code":1445812,"name":"NIKHIL CHANDRAN","email":"NIKHILCHANDRAN@TITAN.CO.IN","level":"L5","dept":"INTERNAL AUDIT","number":9176794284},
{"code":1448257,"name":"VINYASA N PRAKASH","email":"VINYASAPRAKASH@TITAN.CO.IN","level":"L4","dept":"LARGE FORMAT STORES","number":9742395152},
{"code":1448429,"name":"SHRUTI AGRAWAL","email":"SHRUTIAGARWAL@TITAN.CO.IN","level":"L5","dept":"MARKETING-TITAN","number":9902124400},
{"code":1448956,"name":"KIRTI VIKIRNA LAL","email":"KIRTILAL@TITAN.CO.IN","level":"L8","dept":"HUMAN RESOURCES","number":8147006635},
{"code":1450252,"name":"DEEPIKA PATHYA","email":"DEEPIKAP@TITAN.CO.IN","level":"D1","dept":"DESIGNS-TANISHQ","number":7738612610},
{"code":1452140,"name":"SOHINI SINHA","email":"SOHINISINHA@TITAN.CO.IN","level":"L8","dept":"HUMAN RESOURCES","number":9739731777},
{"code":1456185,"name":"DAVANTHI K","email":"DAVANTHI@TITAN.CO.IN","level":"L2","dept":"FINANCE","number":9632551345},
{"code":1458944,"name":"AMRUTHA RAMACHANDRAN","email":"AMRUTHAR@TITAN.CO.IN","level":"L5","dept":"MERCHANDISING - WAD","number":9886856370},
{"code":1459060,"name":"SWATHI C","email":"SWATHIC@TITAN.CO.IN","level":"L4","dept":"RETAIL PROJECTS","number":9886734425},
{"code":1459404,"name":"RAJEEV RANJAN","email":"RAJEEVRANJAN@TITAN.CO.IN","level":"L4","dept":"SYSTEMS","number":8147913405},
{"code":1459673,"name":"ARUN DARWIN H","email":"ARUNDARWIN@TITAN.CO.IN","level":"L5","dept":"E-COMMERCE GENERAL","number":9884358718},
{"code":1469134,"name":"RANA SINGH CHAUHAN","email":"RANA@TITAN.CO.IN","level":"L3","dept":"MARKETING-FASTRACK","number":7042000535},
{"code":1474886,"name":"KURUVILLA MARKOSE","email":"KURUVILLA@TITAN.CO.IN","level":"3","dept":"CORPORATE GENERAL","number":8446021003},
{"code":1475088,"name":"SANJAY NARULA","email":"SANJAYNARULA@TITAN.CO.IN","level":"4","dept":"MERCHANDISING-WAD","number":9611896109},
{"code":1478221,"name":"NIVEDITA SINGHA","email":"NIVEDITAS@TITAN.CO.IN","level":"L2","dept":"FINANCE","number":7406184135}]
